{
"meta":{"test_sets":[],"test_metrics":[],"learn_metrics":[{"best_value":"Min","name":"Logloss"}],"launch_mode":"Train","parameters":"","iteration_count":1000,"learn_sets":["learn"],"name":"experiment"},
"iterations":[
{"learn":[0.6818626881],"iteration":0,"passed_time":0.008018574153,"remaining_time":8.010555578},
{"learn":[0.6697380066],"iteration":1,"passed_time":0.01486368625,"remaining_time":7.416979441},
{"learn":[0.6601867676],"iteration":2,"passed_time":0.02008005891,"remaining_time":6.67327291},
{"learn":[0.6505743027],"iteration":3,"passed_time":0.02707054447,"remaining_time":6.740565573},
{"learn":[0.6410737991],"iteration":4,"passed_time":0.03339115209,"remaining_time":6.644839265},
{"learn":[0.6314709663],"iteration":5,"passed_time":0.04028351504,"remaining_time":6.673635659},
{"learn":[0.6226205349],"iteration":6,"passed_time":0.0462577814,"remaining_time":6.561996704},
{"learn":[0.6122520447],"iteration":7,"passed_time":0.05226669838,"remaining_time":6.481070599},
{"learn":[0.6028688431],"iteration":8,"passed_time":0.05855743796,"remaining_time":6.447824557},
{"learn":[0.5934459686],"iteration":9,"passed_time":0.06435573697,"remaining_time":6.37121796},
{"learn":[0.585273838],"iteration":10,"passed_time":0.0705317953,"remaining_time":6.341449596},
{"learn":[0.576634407],"iteration":11,"passed_time":0.07460916403,"remaining_time":6.142821172},
{"learn":[0.5684563637],"iteration":12,"passed_time":0.08096808901,"remaining_time":6.14734645},
{"learn":[0.5601886749],"iteration":13,"passed_time":0.08639402878,"remaining_time":6.084608027},
{"learn":[0.5508134842],"iteration":14,"passed_time":0.09115494236,"remaining_time":5.985841215},
{"learn":[0.5422742844],"iteration":15,"passed_time":0.09650956585,"remaining_time":5.9353383},
{"learn":[0.5342247486],"iteration":16,"passed_time":0.1023963265,"remaining_time":5.920916994},
{"learn":[0.5259098053],"iteration":17,"passed_time":0.1081199033,"remaining_time":5.89854139},
{"learn":[0.5164166451],"iteration":18,"passed_time":0.1134053497,"remaining_time":5.855297265},
{"learn":[0.5090808868],"iteration":19,"passed_time":0.1187175674,"remaining_time":5.817160802},
{"learn":[0.5023556709],"iteration":20,"passed_time":0.1262040103,"remaining_time":5.883510764},
{"learn":[0.4950152874],"iteration":21,"passed_time":0.1307287946,"remaining_time":5.811489141},
{"learn":[0.4872883797],"iteration":22,"passed_time":0.1360900273,"remaining_time":5.780867683},
{"learn":[0.4783644199],"iteration":23,"passed_time":0.1409457401,"remaining_time":5.731793432},
{"learn":[0.4702512741],"iteration":24,"passed_time":0.1460463032,"remaining_time":5.695805825},
{"learn":[0.463489151],"iteration":25,"passed_time":0.1508697271,"remaining_time":5.651812084},
{"learn":[0.4573630333],"iteration":26,"passed_time":0.1562935102,"remaining_time":5.632355014},
{"learn":[0.4504644394],"iteration":27,"passed_time":0.1618160583,"remaining_time":5.617328882},
{"learn":[0.4430459976],"iteration":28,"passed_time":0.1684568559,"remaining_time":5.640400245},
{"learn":[0.4376832962],"iteration":29,"passed_time":0.1745063703,"remaining_time":5.64237264},
{"learn":[0.4320500851],"iteration":30,"passed_time":0.1806799686,"remaining_time":5.647706115},
{"learn":[0.4260811806],"iteration":31,"passed_time":0.1850992077,"remaining_time":5.599251032},
{"learn":[0.4219589233],"iteration":32,"passed_time":0.1896121368,"remaining_time":5.556210189},
{"learn":[0.4156130791],"iteration":33,"passed_time":0.1958511879,"remaining_time":5.564477868},
{"learn":[0.4102833271],"iteration":34,"passed_time":0.2012919929,"remaining_time":5.549907806},
{"learn":[0.4045190811],"iteration":35,"passed_time":0.2074636795,"remaining_time":5.555416308},
{"learn":[0.399084568],"iteration":36,"passed_time":0.2124989139,"remaining_time":5.530714976},
{"learn":[0.3929230452],"iteration":37,"passed_time":0.2172949765,"remaining_time":5.500993878},
{"learn":[0.3869564056],"iteration":38,"passed_time":0.222448008,"remaining_time":5.481347068},
{"learn":[0.3820258141],"iteration":39,"passed_time":0.2279624968,"remaining_time":5.471099924},
{"learn":[0.3766214609],"iteration":40,"passed_time":0.2335190482,"remaining_time":5.462067492},
{"learn":[0.3708114624],"iteration":41,"passed_time":0.2397159519,"remaining_time":5.467806712},
{"learn":[0.3655306339],"iteration":42,"passed_time":0.2451471626,"remaining_time":5.455949641},
{"learn":[0.3607979536],"iteration":43,"passed_time":0.2512163606,"remaining_time":5.458246381},
{"learn":[0.3565464973],"iteration":44,"passed_time":0.2565558447,"remaining_time":5.444685148},
{"learn":[0.3517640352],"iteration":45,"passed_time":0.2623491111,"remaining_time":5.440892435},
{"learn":[0.347275877],"iteration":46,"passed_time":0.2686893066,"remaining_time":5.44810445},
{"learn":[0.3424926519],"iteration":47,"passed_time":0.2730960888,"remaining_time":5.41640576},
{"learn":[0.3388672352],"iteration":48,"passed_time":0.2792568718,"remaining_time":5.419862961},
{"learn":[0.3346243858],"iteration":49,"passed_time":0.2844160318,"remaining_time":5.403904604},
{"learn":[0.3304465771],"iteration":50,"passed_time":0.2898296988,"remaining_time":5.393105572},
{"learn":[0.3263327599],"iteration":51,"passed_time":0.2954514821,"remaining_time":5.38630779},
{"learn":[0.3219771862],"iteration":52,"passed_time":0.3002278485,"remaining_time":5.364448538},
{"learn":[0.3171794176],"iteration":53,"passed_time":0.3047906685,"remaining_time":5.33948097},
{"learn":[0.3133125067],"iteration":54,"passed_time":0.309767386,"remaining_time":5.322366905},
{"learn":[0.3083181858],"iteration":55,"passed_time":0.3166088622,"remaining_time":5.33712082},
{"learn":[0.3049003839],"iteration":56,"passed_time":0.3212032794,"remaining_time":5.313941974},
{"learn":[0.3011479139],"iteration":57,"passed_time":0.3269419349,"remaining_time":5.309987976},
{"learn":[0.298036623],"iteration":58,"passed_time":0.3286269612,"remaining_time":5.241321533},
{"learn":[0.2937731266],"iteration":59,"passed_time":0.3341144595,"remaining_time":5.234459866},
{"learn":[0.2902816772],"iteration":60,"passed_time":0.3426078373,"remaining_time":5.273914085},
{"learn":[0.2863795757],"iteration":61,"passed_time":0.3477027861,"remaining_time":5.260406667},
{"learn":[0.2826828003],"iteration":62,"passed_time":0.3517150561,"remaining_time":5.231063612},
{"learn":[0.2790559292],"iteration":63,"passed_time":0.3547012026,"remaining_time":5.187505088},
{"learn":[0.2751788616],"iteration":64,"passed_time":0.3581075684,"remaining_time":5.151239637},
{"learn":[0.2720799446],"iteration":65,"passed_time":0.3610866147,"remaining_time":5.109922699},
{"learn":[0.2690168858],"iteration":66,"passed_time":0.363453355,"remaining_time":5.061223586},
{"learn":[0.2652178526],"iteration":67,"passed_time":0.3655908478,"remaining_time":5.01074515},
{"learn":[0.2623619556],"iteration":68,"passed_time":0.3678354651,"remaining_time":4.963113304},
{"learn":[0.258935523],"iteration":69,"passed_time":0.3699970225,"remaining_time":4.915674728},
{"learn":[0.2556951284],"iteration":70,"passed_time":0.372228197,"remaining_time":4.870422465},
{"learn":[0.2528640747],"iteration":71,"passed_time":0.3743666624,"remaining_time":4.825170315},
{"learn":[0.2494063377],"iteration":72,"passed_time":0.3765658613,"remaining_time":4.781870595},
{"learn":[0.2459609509],"iteration":73,"passed_time":0.3788494034,"remaining_time":4.740737129},
{"learn":[0.2427008152],"iteration":74,"passed_time":0.3810697694,"remaining_time":4.699860489},
{"learn":[0.2396296978],"iteration":75,"passed_time":0.382570474,"remaining_time":4.651251553},
{"learn":[0.2359580517],"iteration":76,"passed_time":0.3848511911,"remaining_time":4.613216226},
{"learn":[0.2331064224],"iteration":77,"passed_time":0.3872247873,"remaining_time":4.577195563},
{"learn":[0.2297706604],"iteration":78,"passed_time":0.3897101198,"remaining_time":4.543329371},
{"learn":[0.2270069599],"iteration":79,"passed_time":0.3919460419,"remaining_time":4.507379482},
{"learn":[0.224408865],"iteration":80,"passed_time":0.3942283873,"remaining_time":4.47278874},
{"learn":[0.2215155125],"iteration":81,"passed_time":0.3965394283,"remaining_time":4.439307258},
{"learn":[0.2191475391],"iteration":82,"passed_time":0.3989650896,"remaining_time":4.407843219},
{"learn":[0.2165604115],"iteration":83,"passed_time":0.4012983085,"remaining_time":4.376062507},
{"learn":[0.2144939184],"iteration":84,"passed_time":0.403327526,"remaining_time":4.341702192},
{"learn":[0.2113539696],"iteration":85,"passed_time":0.4054714748,"remaining_time":4.309313116},
{"learn":[0.2090299129],"iteration":86,"passed_time":0.4077213821,"remaining_time":4.278731286},
{"learn":[0.2067967892],"iteration":87,"passed_time":0.4100920308,"remaining_time":4.250044683},
{"learn":[0.2046201229],"iteration":88,"passed_time":0.4121996239,"remaining_time":4.219256825},
{"learn":[0.20207932],"iteration":89,"passed_time":0.414469475,"remaining_time":4.190746914},
{"learn":[0.2000130177],"iteration":90,"passed_time":0.4165867874,"remaining_time":4.161289997},
{"learn":[0.1977364779],"iteration":91,"passed_time":0.4187905631,"remaining_time":4.133280775},
{"learn":[0.1958683968],"iteration":92,"passed_time":0.4209175049,"remaining_time":4.105077171},
{"learn":[0.1932861328],"iteration":93,"passed_time":0.4232351901,"remaining_time":4.079266832},
{"learn":[0.1909483671],"iteration":94,"passed_time":0.4253771164,"remaining_time":4.05227674},
{"learn":[0.1887677312],"iteration":95,"passed_time":0.4276070633,"remaining_time":4.02663318},
{"learn":[0.1864683867],"iteration":96,"passed_time":0.4299513766,"remaining_time":4.002537042},
{"learn":[0.1842797279],"iteration":97,"passed_time":0.4324238063,"remaining_time":3.980064013},
{"learn":[0.1820749521],"iteration":98,"passed_time":0.4346242086,"remaining_time":3.955519312},
{"learn":[0.1800838828],"iteration":99,"passed_time":0.4368279217,"remaining_time":3.931451296},
{"learn":[0.1777789831],"iteration":100,"passed_time":0.4390280965,"remaining_time":3.90778474},
{"learn":[0.1754853964],"iteration":101,"passed_time":0.4411417106,"remaining_time":3.88377702},
{"learn":[0.1730290771],"iteration":102,"passed_time":0.4433402111,"remaining_time":3.860933684},
{"learn":[0.1712086439],"iteration":103,"passed_time":0.4455600288,"remaining_time":3.838671017},
{"learn":[0.1696280956],"iteration":104,"passed_time":0.4478903384,"remaining_time":3.817731932},
{"learn":[0.1681353092],"iteration":105,"passed_time":0.4500588876,"remaining_time":3.795779675},
{"learn":[0.1662918091],"iteration":106,"passed_time":0.4523044366,"remaining_time":3.77483983},
{"learn":[0.1643815279],"iteration":107,"passed_time":0.4543830017,"remaining_time":3.752867014},
{"learn":[0.1621419311],"iteration":108,"passed_time":0.4566274339,"remaining_time":3.732615079},
{"learn":[0.160475421],"iteration":109,"passed_time":0.4587896255,"remaining_time":3.712025152},
{"learn":[0.1587459445],"iteration":110,"passed_time":0.4610308152,"remaining_time":3.692399952},
{"learn":[0.1569879293],"iteration":111,"passed_time":0.4633464912,"remaining_time":3.673675752},
{"learn":[0.1556516647],"iteration":112,"passed_time":0.4648728138,"remaining_time":3.649045893},
{"learn":[0.1539889812],"iteration":113,"passed_time":0.467212682,"remaining_time":3.631144177},
{"learn":[0.152505362],"iteration":114,"passed_time":0.4693178375,"remaining_time":3.611706837},
{"learn":[0.1508227587],"iteration":115,"passed_time":0.4716029538,"remaining_time":3.593939752},
{"learn":[0.148980546],"iteration":116,"passed_time":0.473850907,"remaining_time":3.576156845},
{"learn":[0.1475329161],"iteration":117,"passed_time":0.4760243221,"remaining_time":3.558080103},
{"learn":[0.1459948897],"iteration":118,"passed_time":0.478128651,"remaining_time":3.539759173},
{"learn":[0.1443446517],"iteration":119,"passed_time":0.4803409393,"remaining_time":3.522500222},
{"learn":[0.1427708983],"iteration":120,"passed_time":0.4826188872,"remaining_time":3.505966957},
{"learn":[0.1414114714],"iteration":121,"passed_time":0.4848632411,"remaining_time":3.48942562},
{"learn":[0.1401785851],"iteration":122,"passed_time":0.4871600101,"remaining_time":3.473490479},
{"learn":[0.1385727167],"iteration":123,"passed_time":0.4893433704,"remaining_time":3.456974133},
{"learn":[0.1373863697],"iteration":124,"passed_time":0.4917450272,"remaining_time":3.44221519},
{"learn":[0.1359417439],"iteration":125,"passed_time":0.4938888835,"remaining_time":3.42586416},
{"learn":[0.1344424725],"iteration":126,"passed_time":0.496084609,"remaining_time":3.410093415},
{"learn":[0.1329942226],"iteration":127,"passed_time":0.4981836545,"remaining_time":3.393876146},
{"learn":[0.1315085888],"iteration":128,"passed_time":0.5004699325,"remaining_time":3.379141947},
{"learn":[0.1304100275],"iteration":129,"passed_time":0.5028258317,"remaining_time":3.365065182},
{"learn":[0.1288410783],"iteration":130,"passed_time":0.5049152087,"remaining_time":3.349399361},
{"learn":[0.1275844455],"iteration":131,"passed_time":0.5071060308,"remaining_time":3.334606324},
{"learn":[0.1262437582],"iteration":132,"passed_time":0.509653381,"remaining_time":3.322326927},
{"learn":[0.1248001218],"iteration":133,"passed_time":0.5123464097,"remaining_time":3.31113426},
{"learn":[0.1237318993],"iteration":134,"passed_time":0.5150874659,"remaining_time":3.300375245},
{"learn":[0.122522068],"iteration":135,"passed_time":0.5177753504,"remaining_time":3.289396343},
{"learn":[0.1211882234],"iteration":136,"passed_time":0.5205996156,"remaining_time":3.279397579},
{"learn":[0.1196462512],"iteration":137,"passed_time":0.5234759234,"remaining_time":3.26982787},
{"learn":[0.1180673361],"iteration":138,"passed_time":0.5261277289,"remaining_time":3.258963846},
{"learn":[0.1170455933],"iteration":139,"passed_time":0.5291254156,"remaining_time":3.250341839},
{"learn":[0.1156368613],"iteration":140,"passed_time":0.5320025993,"remaining_time":3.241065481},
{"learn":[0.1145907402],"iteration":141,"passed_time":0.534616934,"remaining_time":3.230291052},
{"learn":[0.113687396],"iteration":142,"passed_time":0.5373270222,"remaining_time":3.220204602},
{"learn":[0.1124804616],"iteration":143,"passed_time":0.540109045,"remaining_time":3.210648212},
{"learn":[0.1113978863],"iteration":144,"passed_time":0.5427397668,"remaining_time":3.200293107},
{"learn":[0.1105578184],"iteration":145,"passed_time":0.545659262,"remaining_time":3.191732944},
{"learn":[0.1092458129],"iteration":146,"passed_time":0.5482603424,"remaining_time":3.181401851},
{"learn":[0.1082635164],"iteration":147,"passed_time":0.5511360669,"remaining_time":3.172756277},
{"learn":[0.1070974708],"iteration":148,"passed_time":0.5537384865,"remaining_time":3.162627194},
{"learn":[0.1062276006],"iteration":149,"passed_time":0.5567240396,"remaining_time":3.154769558},
{"learn":[0.1051494122],"iteration":150,"passed_time":0.5595061566,"remaining_time":3.145832629},
{"learn":[0.1042046428],"iteration":151,"passed_time":0.5617762268,"remaining_time":3.134120002},
{"learn":[0.1028728724],"iteration":152,"passed_time":0.5639127146,"remaining_time":3.121791302},
{"learn":[0.102051878],"iteration":153,"passed_time":0.566164097,"remaining_time":3.110226143},
{"learn":[0.1009586453],"iteration":154,"passed_time":0.568203988,"remaining_time":3.097628193},
{"learn":[0.1001889825],"iteration":155,"passed_time":0.5707639793,"remaining_time":3.087979478},
{"learn":[0.09936810732],"iteration":156,"passed_time":0.5726371457,"remaining_time":3.074733209},
{"learn":[0.09843036532],"iteration":157,"passed_time":0.5748911898,"remaining_time":3.063660644},
{"learn":[0.09739341736],"iteration":158,"passed_time":0.5771070298,"remaining_time":3.052496931},
{"learn":[0.09658498764],"iteration":159,"passed_time":0.5792940952,"remaining_time":3.041294},
{"learn":[0.09564372301],"iteration":160,"passed_time":0.581433153,"remaining_time":3.029952891},
{"learn":[0.09494508505],"iteration":161,"passed_time":0.5836277069,"remaining_time":3.019012459},
{"learn":[0.09409685731],"iteration":162,"passed_time":0.5857857017,"remaining_time":3.00799161},
{"learn":[0.09345897436],"iteration":163,"passed_time":0.5879746005,"remaining_time":2.997236378},
{"learn":[0.09255082011],"iteration":164,"passed_time":0.5901159659,"remaining_time":2.986344433},
{"learn":[0.09149816632],"iteration":165,"passed_time":0.5923289801,"remaining_time":2.975917888},
{"learn":[0.09054356813],"iteration":166,"passed_time":0.5945479527,"remaining_time":2.965619429},
{"learn":[0.08978562355],"iteration":167,"passed_time":0.5968109486,"remaining_time":2.955635174},
{"learn":[0.08895531893],"iteration":168,"passed_time":0.5989475331,"remaining_time":2.94512071},
{"learn":[0.08817803264],"iteration":169,"passed_time":0.6011675657,"remaining_time":2.935112233},
{"learn":[0.08743362427],"iteration":170,"passed_time":0.603359592,"remaining_time":2.925059075},
{"learn":[0.08647264838],"iteration":171,"passed_time":0.605449734,"remaining_time":2.914606859},
{"learn":[0.08578019142],"iteration":172,"passed_time":0.6076794309,"remaining_time":2.904918436},
{"learn":[0.08513738513],"iteration":173,"passed_time":0.6099994596,"remaining_time":2.895744561},
{"learn":[0.08451963663],"iteration":174,"passed_time":0.6122190747,"remaining_time":2.886175638},
{"learn":[0.08368024826],"iteration":175,"passed_time":0.6143129659,"remaining_time":2.876101613},
{"learn":[0.08301707506],"iteration":176,"passed_time":0.6164429327,"remaining_time":2.866285501},
{"learn":[0.08230353594],"iteration":177,"passed_time":0.6187257423,"remaining_time":2.857261574},
{"learn":[0.08169757128],"iteration":178,"passed_time":0.6208566825,"remaining_time":2.847616404},
{"learn":[0.08114309907],"iteration":179,"passed_time":0.6230905796,"remaining_time":2.838523751},
{"learn":[0.08020343184],"iteration":180,"passed_time":0.6252465219,"remaining_time":2.829154152},
{"learn":[0.07937226892],"iteration":181,"passed_time":0.6273721862,"remaining_time":2.819727738},
{"learn":[0.0785931468],"iteration":182,"passed_time":0.629683313,"remaining_time":2.811209108},
{"learn":[0.07796990871],"iteration":183,"passed_time":0.631972346,"remaining_time":2.802659969},
{"learn":[0.07710598707],"iteration":184,"passed_time":0.6341210132,"remaining_time":2.793560139},
{"learn":[0.07649277449],"iteration":185,"passed_time":0.6364031736,"remaining_time":2.785119265},
{"learn":[0.07602367401],"iteration":186,"passed_time":0.6385688703,"remaining_time":2.776237923},
{"learn":[0.07519711256],"iteration":187,"passed_time":0.6407978773,"remaining_time":2.76770147},
{"learn":[0.07474719286],"iteration":188,"passed_time":0.6435666165,"remaining_time":2.761547756},
{"learn":[0.07413007617],"iteration":189,"passed_time":0.6456132043,"remaining_time":2.752351029},
{"learn":[0.07342318296],"iteration":190,"passed_time":0.6477540147,"remaining_time":2.743628261},
{"learn":[0.07288645506],"iteration":191,"passed_time":0.650008513,"remaining_time":2.735452492},
{"learn":[0.07232893109],"iteration":192,"passed_time":0.652202091,"remaining_time":2.727083354},
{"learn":[0.07154797912],"iteration":193,"passed_time":0.6543845729,"remaining_time":2.718731782},
{"learn":[0.07111001015],"iteration":194,"passed_time":0.6566080456,"remaining_time":2.710612701},
{"learn":[0.07068755627],"iteration":195,"passed_time":0.6588186656,"remaining_time":2.702501057},
{"learn":[0.07002762556],"iteration":196,"passed_time":0.6611157913,"remaining_time":2.694801931},
{"learn":[0.06944459677],"iteration":197,"passed_time":0.6633605219,"remaining_time":2.686945144},
{"learn":[0.06887651682],"iteration":198,"passed_time":0.6656519158,"remaining_time":2.679332586},
{"learn":[0.06838406324],"iteration":199,"passed_time":0.6677509979,"remaining_time":2.671003992},
{"learn":[0.06786521077],"iteration":200,"passed_time":0.6701544064,"remaining_time":2.663947118},
{"learn":[0.06734905839],"iteration":201,"passed_time":0.6723134621,"remaining_time":2.655971004},
{"learn":[0.06695075631],"iteration":202,"passed_time":0.674416266,"remaining_time":2.64783135},
{"learn":[0.06639623046],"iteration":203,"passed_time":0.6764772199,"remaining_time":2.639587584},
{"learn":[0.06590958834],"iteration":204,"passed_time":0.6785483823,"remaining_time":2.631443727},
{"learn":[0.065444839],"iteration":205,"passed_time":0.6807474529,"remaining_time":2.623851833},
{"learn":[0.06484755874],"iteration":206,"passed_time":0.6829813467,"remaining_time":2.616445449},
{"learn":[0.06428830624],"iteration":207,"passed_time":0.6852703872,"remaining_time":2.609298782},
{"learn":[0.06372841597],"iteration":208,"passed_time":0.6875527077,"remaining_time":2.602173166},
{"learn":[0.06322822571],"iteration":209,"passed_time":0.6898911491,"remaining_time":2.595304799},
{"learn":[0.06275656223],"iteration":210,"passed_time":0.6920294986,"remaining_time":2.587731158},
{"learn":[0.06217427254],"iteration":211,"passed_time":0.6940795707,"remaining_time":2.579880668},
{"learn":[0.06175585985],"iteration":212,"passed_time":0.6961145525,"remaining_time":2.572028886},
{"learn":[0.06142297983],"iteration":213,"passed_time":0.6983239516,"remaining_time":2.564872084},
{"learn":[0.06093702316],"iteration":214,"passed_time":0.7005287581,"remaining_time":2.557744535},
{"learn":[0.06066179276],"iteration":215,"passed_time":0.7027024316,"remaining_time":2.550549566},
{"learn":[0.0603146553],"iteration":216,"passed_time":0.7049557065,"remaining_time":2.543688102},
{"learn":[0.05987057686],"iteration":217,"passed_time":0.7070425501,"remaining_time":2.5362719},
{"learn":[0.05953044891],"iteration":218,"passed_time":0.7092034441,"remaining_time":2.529168447},
{"learn":[0.05909087658],"iteration":219,"passed_time":0.7113612156,"remaining_time":2.522098855},
{"learn":[0.05866205692],"iteration":220,"passed_time":0.7135008793,"remaining_time":2.515009887},
{"learn":[0.05810258985],"iteration":221,"passed_time":0.7158442617,"remaining_time":2.50867944},
{"learn":[0.05774164796],"iteration":222,"passed_time":0.7182649163,"remaining_time":2.502653991},
{"learn":[0.05723029375],"iteration":223,"passed_time":0.7205873033,"remaining_time":2.496320301},
{"learn":[0.05690686107],"iteration":224,"passed_time":0.7229229939,"remaining_time":2.49006809},
{"learn":[0.05642826557],"iteration":225,"passed_time":0.725043668,"remaining_time":2.483114155},
{"learn":[0.05588803291],"iteration":226,"passed_time":0.727172864,"remaining_time":2.476231823},
{"learn":[0.05554795265],"iteration":227,"passed_time":0.7294120329,"remaining_time":2.46976355},
{"learn":[0.0550989151],"iteration":228,"passed_time":0.7316388065,"remaining_time":2.463290479},
{"learn":[0.05460295677],"iteration":229,"passed_time":0.7337651441,"remaining_time":2.456518091},
{"learn":[0.0542516768],"iteration":230,"passed_time":0.7360891903,"remaining_time":2.450444101},
{"learn":[0.05373574495],"iteration":231,"passed_time":0.7382930101,"remaining_time":2.444004447},
{"learn":[0.05336755514],"iteration":232,"passed_time":0.7406878059,"remaining_time":2.438229816},
{"learn":[0.05305188894],"iteration":233,"passed_time":0.7428632327,"remaining_time":2.431765967},
{"learn":[0.05265769958],"iteration":234,"passed_time":0.7449899087,"remaining_time":2.425179916},
{"learn":[0.05230227709],"iteration":235,"passed_time":0.7473308243,"remaining_time":2.419325211},
{"learn":[0.05183585882],"iteration":236,"passed_time":0.7494886234,"remaining_time":2.412910631},
{"learn":[0.05154474974],"iteration":237,"passed_time":0.751771828,"remaining_time":2.406933332},
{"learn":[0.05128188729],"iteration":238,"passed_time":0.7539093958,"remaining_time":2.400523223},
{"learn":[0.0510055542],"iteration":239,"passed_time":0.7560464028,"remaining_time":2.394146942},
{"learn":[0.05063468218],"iteration":240,"passed_time":0.7581642552,"remaining_time":2.387745518},
{"learn":[0.05023645759],"iteration":241,"passed_time":0.7602901612,"remaining_time":2.38140472},
{"learn":[0.049932006],"iteration":242,"passed_time":0.7626775927,"remaining_time":2.375913324},
{"learn":[0.04968596697],"iteration":243,"passed_time":0.7649320301,"remaining_time":2.370035306},
{"learn":[0.04940419793],"iteration":244,"passed_time":0.7671664672,"remaining_time":2.364125236},
{"learn":[0.04896298647],"iteration":245,"passed_time":0.7692498573,"remaining_time":2.357782083},
{"learn":[0.04868898392],"iteration":246,"passed_time":0.7713573388,"remaining_time":2.351546867},
{"learn":[0.04838236272],"iteration":247,"passed_time":0.7735977093,"remaining_time":2.345747893},
{"learn":[0.0480464071],"iteration":248,"passed_time":0.7758495117,"remaining_time":2.340011981},
{"learn":[0.04770742059],"iteration":249,"passed_time":0.7780337228,"remaining_time":2.334101168},
{"learn":[0.04739880562],"iteration":250,"passed_time":0.7804267478,"remaining_time":2.328843164},
{"learn":[0.04707547724],"iteration":251,"passed_time":0.78266787,"remaining_time":2.323157011},
{"learn":[0.04691256881],"iteration":252,"passed_time":0.7848970028,"remaining_time":2.317462692},
{"learn":[0.04666385055],"iteration":253,"passed_time":0.7870724996,"remaining_time":2.311638129},
{"learn":[0.0463475734],"iteration":254,"passed_time":0.7893141243,"remaining_time":2.306035383},
{"learn":[0.04612683058],"iteration":255,"passed_time":0.7916650901,"remaining_time":2.300776668},
{"learn":[0.0458694607],"iteration":256,"passed_time":0.7936869684,"remaining_time":2.294589173},
{"learn":[0.04552715123],"iteration":257,"passed_time":0.7959700688,"remaining_time":2.289185237},
{"learn":[0.04525582194],"iteration":258,"passed_time":0.7982132802,"remaining_time":2.283691277},
{"learn":[0.04495820999],"iteration":259,"passed_time":0.8003716309,"remaining_time":2.277980796},
{"learn":[0.04463695884],"iteration":260,"passed_time":0.8025972786,"remaining_time":2.27248808},
{"learn":[0.04443781972],"iteration":261,"passed_time":0.8046536408,"remaining_time":2.266543462},
{"learn":[0.04421616793],"iteration":262,"passed_time":0.8067904428,"remaining_time":2.260853826},
{"learn":[0.04399885237],"iteration":263,"passed_time":0.8089075852,"remaining_time":2.255136298},
{"learn":[0.04379578233],"iteration":264,"passed_time":0.8112427558,"remaining_time":2.250050662},
{"learn":[0.04354207516],"iteration":265,"passed_time":0.81345848,"remaining_time":2.244656107},
{"learn":[0.04330141544],"iteration":266,"passed_time":0.8155506803,"remaining_time":2.23894625},
{"learn":[0.04307020903],"iteration":267,"passed_time":0.8176268712,"remaining_time":2.233219663},
{"learn":[0.04277566075],"iteration":268,"passed_time":0.8198962389,"remaining_time":2.22804517},
{"learn":[0.0425337702],"iteration":269,"passed_time":0.8220729049,"remaining_time":2.222641558},
{"learn":[0.0422819525],"iteration":270,"passed_time":0.8242750389,"remaining_time":2.217330271},
{"learn":[0.04197797179],"iteration":271,"passed_time":0.8265930617,"remaining_time":2.212352018},
{"learn":[0.04165556133],"iteration":272,"passed_time":0.8289839174,"remaining_time":2.207587209},
{"learn":[0.04147409797],"iteration":273,"passed_time":0.8309237108,"remaining_time":2.201644577},
{"learn":[0.04127283692],"iteration":274,"passed_time":0.8331818466,"remaining_time":2.196570323},
{"learn":[0.04103793204],"iteration":275,"passed_time":0.8353091443,"remaining_time":2.191173263},
{"learn":[0.04076747894],"iteration":276,"passed_time":0.8375846138,"remaining_time":2.186186555},
{"learn":[0.04049111903],"iteration":277,"passed_time":0.8398619366,"remaining_time":2.181224166},
{"learn":[0.04029118419],"iteration":278,"passed_time":0.8420452402,"remaining_time":2.176038058},
{"learn":[0.04007510543],"iteration":279,"passed_time":0.8440659509,"remaining_time":2.170455302},
{"learn":[0.039878425],"iteration":280,"passed_time":0.8463507098,"remaining_time":2.165573524},
{"learn":[0.03964936435],"iteration":281,"passed_time":0.8485593222,"remaining_time":2.160516288},
{"learn":[0.03945914209],"iteration":282,"passed_time":0.8508676981,"remaining_time":2.155731942},
{"learn":[0.0392531842],"iteration":283,"passed_time":0.8530000558,"remaining_time":2.150521267},
{"learn":[0.03904233277],"iteration":284,"passed_time":0.8551557506,"remaining_time":2.145390743},
{"learn":[0.03876386285],"iteration":285,"passed_time":0.8574391202,"remaining_time":2.140599762},
{"learn":[0.0385487318],"iteration":286,"passed_time":0.8598533356,"remaining_time":2.136151318},
{"learn":[0.03825691342],"iteration":287,"passed_time":0.8620296349,"remaining_time":2.13112882},
{"learn":[0.03805195391],"iteration":288,"passed_time":0.8642597411,"remaining_time":2.126258394},
{"learn":[0.03785026073],"iteration":289,"passed_time":0.8663570773,"remaining_time":2.12108112},
{"learn":[0.03762679696],"iteration":290,"passed_time":0.869104947,"remaining_time":2.117509991},
{"learn":[0.03742191494],"iteration":291,"passed_time":0.8713135311,"remaining_time":2.112636918},
{"learn":[0.03720707297],"iteration":292,"passed_time":0.873427951,"remaining_time":2.107554817},
{"learn":[0.03694468737],"iteration":293,"passed_time":0.8755911018,"remaining_time":2.102609925},
{"learn":[0.03680921793],"iteration":294,"passed_time":0.8777783638,"remaining_time":2.097741514},
{"learn":[0.03657815456],"iteration":295,"passed_time":0.8799136258,"remaining_time":2.092767542},
{"learn":[0.03635578156],"iteration":296,"passed_time":0.8821650707,"remaining_time":2.088087692},
{"learn":[0.03616273105],"iteration":297,"passed_time":0.8846533023,"remaining_time":2.08398194},
{"learn":[0.035953632],"iteration":298,"passed_time":0.8870759019,"remaining_time":2.079733135},
{"learn":[0.0357774049],"iteration":299,"passed_time":0.8890477593,"remaining_time":2.074444772},
{"learn":[0.03555699587],"iteration":300,"passed_time":0.8912142076,"remaining_time":2.069630336},
{"learn":[0.03534147739],"iteration":301,"passed_time":0.8933925445,"remaining_time":2.064860914},
{"learn":[0.03515161276],"iteration":302,"passed_time":0.8953993616,"remaining_time":2.059714043},
{"learn":[0.03500621915],"iteration":303,"passed_time":0.8977583584,"remaining_time":2.055394136},
{"learn":[0.03479594588],"iteration":304,"passed_time":0.899799697,"remaining_time":2.050363244},
{"learn":[0.034626472],"iteration":305,"passed_time":0.9019503301,"remaining_time":2.045599768},
{"learn":[0.03437544405],"iteration":306,"passed_time":0.9043396108,"remaining_time":2.04139202},
{"learn":[0.03416024446],"iteration":307,"passed_time":0.9065274178,"remaining_time":2.036743419},
{"learn":[0.0339459002],"iteration":308,"passed_time":0.9087016421,"remaining_time":2.032080371},
{"learn":[0.03375419676],"iteration":309,"passed_time":0.9109005936,"remaining_time":2.027488418},
{"learn":[0.03351043165],"iteration":310,"passed_time":0.9131224804,"remaining_time":2.022962666},
{"learn":[0.033351928],"iteration":311,"passed_time":0.9153158009,"remaining_time":2.018388689},
{"learn":[0.03319094479],"iteration":312,"passed_time":0.917488391,"remaining_time":2.013784424},
{"learn":[0.03302839398],"iteration":313,"passed_time":0.9197336291,"remaining_time":2.009354362},
{"learn":[0.03291770816],"iteration":314,"passed_time":0.9219699154,"remaining_time":2.004918705},
{"learn":[0.03274044991],"iteration":315,"passed_time":0.9240402645,"remaining_time":2.000137788},
{"learn":[0.03259444833],"iteration":316,"passed_time":0.9262997712,"remaining_time":1.995781526},
{"learn":[0.03242760599],"iteration":317,"passed_time":0.9287815819,"remaining_time":1.991915216},
{"learn":[0.03224785626],"iteration":318,"passed_time":0.9308624603,"remaining_time":1.987201679},
{"learn":[0.03207140267],"iteration":319,"passed_time":0.9329191067,"remaining_time":1.982453102},
{"learn":[0.03192459345],"iteration":320,"passed_time":0.9352620615,"remaining_time":1.978326915},
{"learn":[0.03177938461],"iteration":321,"passed_time":0.9377036657,"remaining_time":1.97441952},
{"learn":[0.03164256811],"iteration":322,"passed_time":0.9400775261,"remaining_time":1.970379211},
{"learn":[0.03150331974],"iteration":323,"passed_time":0.9422445145,"remaining_time":1.965917567},
{"learn":[0.03135766983],"iteration":324,"passed_time":0.9443844007,"remaining_time":1.961413755},
{"learn":[0.03120589852],"iteration":325,"passed_time":0.9465931556,"remaining_time":1.957066831},
{"learn":[0.03104031384],"iteration":326,"passed_time":0.9487396111,"remaining_time":1.952604765},
{"learn":[0.03091178834],"iteration":327,"passed_time":0.9510693765,"remaining_time":1.948532381},
{"learn":[0.0307597518],"iteration":328,"passed_time":0.9531946508,"remaining_time":1.944053528},
{"learn":[0.0305853188],"iteration":329,"passed_time":0.9554672552,"remaining_time":1.939888064},
{"learn":[0.0304312408],"iteration":330,"passed_time":0.9577563349,"remaining_time":1.935767336},
{"learn":[0.03030199707],"iteration":331,"passed_time":0.9597960935,"remaining_time":1.931155995},
{"learn":[0.03018601537],"iteration":332,"passed_time":0.9621414867,"remaining_time":1.927172287},
{"learn":[0.03006491661],"iteration":333,"passed_time":0.9643235129,"remaining_time":1.922872633},
{"learn":[0.02995035052],"iteration":334,"passed_time":0.9664838152,"remaining_time":1.918542499},
{"learn":[0.02978013158],"iteration":335,"passed_time":0.9687343243,"remaining_time":1.914403546},
{"learn":[0.02965329289],"iteration":336,"passed_time":0.970887319,"remaining_time":1.910083954},
{"learn":[0.02951810062],"iteration":337,"passed_time":0.9729755893,"remaining_time":1.905650415},
{"learn":[0.02937405109],"iteration":338,"passed_time":0.9753199175,"remaining_time":1.901729987},
{"learn":[0.02928426862],"iteration":339,"passed_time":0.9775101046,"remaining_time":1.897519615},
{"learn":[0.02913985252],"iteration":340,"passed_time":0.9796070992,"remaining_time":1.893140992},
{"learn":[0.02895500958],"iteration":341,"passed_time":0.9819039124,"remaining_time":1.889160159},
{"learn":[0.02883312106],"iteration":342,"passed_time":0.9840633231,"remaining_time":1.884925957},
{"learn":[0.02869792581],"iteration":343,"passed_time":0.9863411118,"remaining_time":1.880929562},
{"learn":[0.02854994535],"iteration":344,"passed_time":0.9885644412,"remaining_time":1.876839736},
{"learn":[0.02840037942],"iteration":345,"passed_time":0.9908284288,"remaining_time":1.87283755},
{"learn":[0.02828992605],"iteration":346,"passed_time":0.9930230359,"remaining_time":1.86871482},
{"learn":[0.02815284133],"iteration":347,"passed_time":0.995304068,"remaining_time":1.864765093},
{"learn":[0.02802349031],"iteration":348,"passed_time":0.9975295416,"remaining_time":1.860721294},
{"learn":[0.02789005637],"iteration":349,"passed_time":0.9996443657,"remaining_time":1.856482393},
{"learn":[0.02773787379],"iteration":350,"passed_time":1.00216734,"remaining_time":1.853010266},
{"learn":[0.02760857344],"iteration":351,"passed_time":1.004158595,"remaining_time":1.848564686},
{"learn":[0.02743623257],"iteration":352,"passed_time":1.006407161,"remaining_time":1.844604627},
{"learn":[0.02734193802],"iteration":353,"passed_time":1.008614841,"remaining_time":1.840579625},
{"learn":[0.02722553611],"iteration":354,"passed_time":1.010913718,"remaining_time":1.836730558},
{"learn":[0.02709972858],"iteration":355,"passed_time":1.012957201,"remaining_time":1.832428196},
{"learn":[0.02696549892],"iteration":356,"passed_time":1.015185496,"remaining_time":1.828471355},
{"learn":[0.02683571875],"iteration":357,"passed_time":1.017389862,"remaining_time":1.82448126},
{"learn":[0.02670766115],"iteration":358,"passed_time":1.019584675,"remaining_time":1.820484058},
{"learn":[0.02658889592],"iteration":359,"passed_time":1.021831374,"remaining_time":1.81658911},
{"learn":[0.0264772594],"iteration":360,"passed_time":1.024176346,"remaining_time":1.812877244},
{"learn":[0.02634384632],"iteration":361,"passed_time":1.02634512,"remaining_time":1.808862394},
{"learn":[0.02622315288],"iteration":362,"passed_time":1.028527045,"remaining_time":1.804880792},
{"learn":[0.02603904009],"iteration":363,"passed_time":1.030183896,"remaining_time":1.799991643},
{"learn":[0.0259288609],"iteration":364,"passed_time":1.032464175,"remaining_time":1.796204797},
{"learn":[0.02581352592],"iteration":365,"passed_time":1.034824075,"remaining_time":1.792564108},
{"learn":[0.02568675876],"iteration":366,"passed_time":1.036945996,"remaining_time":1.788519933},
{"learn":[0.02558784187],"iteration":367,"passed_time":1.039309621,"remaining_time":1.784901306},
{"learn":[0.02545054853],"iteration":368,"passed_time":1.041481167,"remaining_time":1.78096102},
{"learn":[0.0253520906],"iteration":369,"passed_time":1.043562461,"remaining_time":1.776876624},
{"learn":[0.02523874044],"iteration":370,"passed_time":1.045839773,"remaining_time":1.773135356},
{"learn":[0.02512234449],"iteration":371,"passed_time":1.048267784,"remaining_time":1.769656367},
{"learn":[0.02497987896],"iteration":372,"passed_time":1.050651249,"remaining_time":1.766108131},
{"learn":[0.0248715505],"iteration":373,"passed_time":1.053051045,"remaining_time":1.762593461},
{"learn":[0.02476392984],"iteration":374,"passed_time":1.055252471,"remaining_time":1.758754119},
{"learn":[0.02467192709],"iteration":375,"passed_time":1.057179669,"remaining_time":1.754468387},
{"learn":[0.02457970232],"iteration":376,"passed_time":1.059422847,"remaining_time":1.75071733},
{"learn":[0.02444072515],"iteration":377,"passed_time":1.061684467,"remaining_time":1.747004598},
{"learn":[0.0243417114],"iteration":378,"passed_time":1.063869893,"remaining_time":1.743174679},
{"learn":[0.02424263954],"iteration":379,"passed_time":1.065855914,"remaining_time":1.73902807},
{"learn":[0.02414547056],"iteration":380,"passed_time":1.068146655,"remaining_time":1.735387873},
{"learn":[0.02402909249],"iteration":381,"passed_time":1.070440143,"remaining_time":1.731759185},
{"learn":[0.02391544878],"iteration":382,"passed_time":1.071725367,"remaining_time":1.72651319},
{"learn":[0.0237756893],"iteration":383,"passed_time":1.074148747,"remaining_time":1.723113615},
{"learn":[0.02367684245],"iteration":384,"passed_time":1.076806898,"remaining_time":1.720094135},
{"learn":[0.02357763648],"iteration":385,"passed_time":1.079122988,"remaining_time":1.716532421},
{"learn":[0.02348170727],"iteration":386,"passed_time":1.081297237,"remaining_time":1.712752471},
{"learn":[0.02335217595],"iteration":387,"passed_time":1.083457022,"remaining_time":1.708957983},
{"learn":[0.02328244597],"iteration":388,"passed_time":1.085474398,"remaining_time":1.704948218},
{"learn":[0.02318174541],"iteration":389,"passed_time":1.087634682,"remaining_time":1.701172194},
{"learn":[0.02308885157],"iteration":390,"passed_time":1.089727894,"remaining_time":1.697299969},
{"learn":[0.02300178409],"iteration":391,"passed_time":1.091961353,"remaining_time":1.693654344},
{"learn":[0.02290605605],"iteration":392,"passed_time":1.094118961,"remaining_time":1.689898751},
{"learn":[0.02278314829],"iteration":393,"passed_time":1.096309415,"remaining_time":1.686201791},
{"learn":[0.02268141508],"iteration":394,"passed_time":1.098490942,"remaining_time":1.682498785},
{"learn":[0.02261245847],"iteration":395,"passed_time":1.100726727,"remaining_time":1.678886219},
{"learn":[0.02249574959],"iteration":396,"passed_time":1.102989199,"remaining_time":1.675321126},
{"learn":[0.02240411937],"iteration":397,"passed_time":1.10506213,"remaining_time":1.671475885},
{"learn":[0.02230275273],"iteration":398,"passed_time":1.107334122,"remaining_time":1.667939367},
{"learn":[0.02218459398],"iteration":399,"passed_time":1.109557948,"remaining_time":1.664336922},
{"learn":[0.02208084613],"iteration":400,"passed_time":1.111646002,"remaining_time":1.660538542},
{"learn":[0.02198506594],"iteration":401,"passed_time":1.113864738,"remaining_time":1.656943067},
{"learn":[0.02187559009],"iteration":402,"passed_time":1.116204511,"remaining_time":1.653533729},
{"learn":[0.02176290452],"iteration":403,"passed_time":1.118484324,"remaining_time":1.65004123},
{"learn":[0.0216623947],"iteration":404,"passed_time":1.120738424,"remaining_time":1.646516944},
{"learn":[0.02159160376],"iteration":405,"passed_time":1.122885892,"remaining_time":1.642842905},
{"learn":[0.02150173038],"iteration":406,"passed_time":1.125077089,"remaining_time":1.639240084},
{"learn":[0.02142596096],"iteration":407,"passed_time":1.127243354,"remaining_time":1.635608003},
{"learn":[0.0213644594],"iteration":408,"passed_time":1.129322823,"remaining_time":1.631857673},
{"learn":[0.02128671855],"iteration":409,"passed_time":1.1313349,"remaining_time":1.628018515},
{"learn":[0.02120420337],"iteration":410,"passed_time":1.133020881,"remaining_time":1.623720921},
{"learn":[0.02113426924],"iteration":411,"passed_time":1.135266941,"remaining_time":1.620235343},
{"learn":[0.02103761584],"iteration":412,"passed_time":1.137572375,"remaining_time":1.616840155},
{"learn":[0.02097411156],"iteration":413,"passed_time":1.139853985,"remaining_time":1.61341651},
{"learn":[0.02089626491],"iteration":414,"passed_time":1.142006992,"remaining_time":1.609817085},
{"learn":[0.02083448768],"iteration":415,"passed_time":1.144140247,"remaining_time":1.606196885},
{"learn":[0.02073786259],"iteration":416,"passed_time":1.146453213,"remaining_time":1.602835067},
{"learn":[0.02065147758],"iteration":417,"passed_time":1.14858554,"remaining_time":1.599226756},
{"learn":[0.02056650221],"iteration":418,"passed_time":1.150676246,"remaining_time":1.595567777},
{"learn":[0.02047836185],"iteration":419,"passed_time":1.152972067,"remaining_time":1.592199521},
{"learn":[0.02041113973],"iteration":420,"passed_time":1.155196552,"remaining_time":1.58873825},
{"learn":[0.02034479678],"iteration":421,"passed_time":1.157523889,"remaining_time":1.585423716},
{"learn":[0.02026939541],"iteration":422,"passed_time":1.159625742,"remaining_time":1.581806273},
{"learn":[0.02020966113],"iteration":423,"passed_time":1.1617898,"remaining_time":1.578280483},
{"learn":[0.02014469355],"iteration":424,"passed_time":1.16398353,"remaining_time":1.574801247},
{"learn":[0.02002979368],"iteration":425,"passed_time":1.166477572,"remaining_time":1.571732691},
{"learn":[0.01996210963],"iteration":426,"passed_time":1.168483598,"remaining_time":1.568011948},
{"learn":[0.01988207102],"iteration":427,"passed_time":1.170724961,"remaining_time":1.564613732},
{"learn":[0.01981061846],"iteration":428,"passed_time":1.172754892,"remaining_time":1.560939494},
{"learn":[0.0197439],"iteration":429,"passed_time":1.175005401,"remaining_time":1.5575653},
{"learn":[0.01968072653],"iteration":430,"passed_time":1.177198461,"remaining_time":1.554120474},
{"learn":[0.01958726496],"iteration":431,"passed_time":1.179453744,"remaining_time":1.550763256},
{"learn":[0.01950605363],"iteration":432,"passed_time":1.181745973,"remaining_time":1.547459508},
{"learn":[0.01943840981],"iteration":433,"passed_time":1.183734112,"remaining_time":1.543763842},
{"learn":[0.019373478],"iteration":434,"passed_time":1.18591788,"remaining_time":1.540330121},
{"learn":[0.01931875199],"iteration":435,"passed_time":1.188152936,"remaining_time":1.536968477},
{"learn":[0.01925436854],"iteration":436,"passed_time":1.190231233,"remaining_time":1.533410032},
{"learn":[0.01918948591],"iteration":437,"passed_time":1.192369354,"remaining_time":1.529935107},
{"learn":[0.01911995709],"iteration":438,"passed_time":1.194503227,"remaining_time":1.526460844},
{"learn":[0.01902715564],"iteration":439,"passed_time":1.196633753,"remaining_time":1.522988413},
{"learn":[0.01898224354],"iteration":440,"passed_time":1.198884542,"remaining_time":1.51967451},
{"learn":[0.01890959293],"iteration":441,"passed_time":1.200954181,"remaining_time":1.516136727},
{"learn":[0.0188432157],"iteration":442,"passed_time":1.203332063,"remaining_time":1.512993135},
{"learn":[0.01874012798],"iteration":443,"passed_time":1.205541493,"remaining_time":1.509642049},
{"learn":[0.01866185963],"iteration":444,"passed_time":1.207781467,"remaining_time":1.50633419},
{"learn":[0.01859316826],"iteration":445,"passed_time":1.21025121,"remaining_time":1.503316526},
{"learn":[0.01852906644],"iteration":446,"passed_time":1.212435096,"remaining_time":1.499947669},
{"learn":[0.01846535802],"iteration":447,"passed_time":1.214462432,"remaining_time":1.496391211},
{"learn":[0.01838971823],"iteration":448,"passed_time":1.216659617,"remaining_time":1.493049998},
{"learn":[0.01833869219],"iteration":449,"passed_time":1.219129294,"remaining_time":1.490046915},
{"learn":[0.01828259826],"iteration":450,"passed_time":1.221256769,"remaining_time":1.486629637},
{"learn":[0.01822213829],"iteration":451,"passed_time":1.22321297,"remaining_time":1.483010415},
{"learn":[0.01816678047],"iteration":452,"passed_time":1.225427071,"remaining_time":1.479709951},
{"learn":[0.01810152084],"iteration":453,"passed_time":1.227486031,"remaining_time":1.476227694},
{"learn":[0.01804115921],"iteration":454,"passed_time":1.229506719,"remaining_time":1.472705851},
{"learn":[0.01797115207],"iteration":455,"passed_time":1.23159291,"remaining_time":1.469268734},
{"learn":[0.017916812],"iteration":456,"passed_time":1.233804483,"remaining_time":1.465986508},
{"learn":[0.0178453818],"iteration":457,"passed_time":1.235919184,"remaining_time":1.462594318},
{"learn":[0.01777660847],"iteration":458,"passed_time":1.238150165,"remaining_time":1.459344748},
{"learn":[0.01770015955],"iteration":459,"passed_time":1.240236828,"remaining_time":1.45593019},
{"learn":[0.0176400274],"iteration":460,"passed_time":1.242345837,"remaining_time":1.452547518},
{"learn":[0.01755822748],"iteration":461,"passed_time":1.244381875,"remaining_time":1.449085387},
{"learn":[0.01750553399],"iteration":462,"passed_time":1.24666289,"remaining_time":1.445913546},
{"learn":[0.01743812561],"iteration":463,"passed_time":1.249144712,"remaining_time":1.442977512},
{"learn":[0.0173707515],"iteration":464,"passed_time":1.251045645,"remaining_time":1.439375097},
{"learn":[0.01731871963],"iteration":465,"passed_time":1.25317166,"remaining_time":1.436037911},
{"learn":[0.01726499498],"iteration":466,"passed_time":1.255183903,"remaining_time":1.43257606},
{"learn":[0.01721490771],"iteration":467,"passed_time":1.257372143,"remaining_time":1.42932047},
{"learn":[0.01716284454],"iteration":468,"passed_time":1.259740314,"remaining_time":1.426273149},
{"learn":[0.01709337682],"iteration":469,"passed_time":1.261692032,"remaining_time":1.4227591},
{"learn":[0.01704355478],"iteration":470,"passed_time":1.263842414,"remaining_time":1.419474813},
{"learn":[0.01700723767],"iteration":471,"passed_time":1.266126381,"remaining_time":1.416344766},
{"learn":[0.01694033593],"iteration":472,"passed_time":1.268392366,"remaining_time":1.41319826},
{"learn":[0.01687399447],"iteration":473,"passed_time":1.270420612,"remaining_time":1.40979165},
{"learn":[0.01680748761],"iteration":474,"passed_time":1.272435417,"remaining_time":1.406375987},
{"learn":[0.0167481944],"iteration":475,"passed_time":1.274599756,"remaining_time":1.403130824},
{"learn":[0.016677472],"iteration":476,"passed_time":1.276542355,"remaining_time":1.399647068},
{"learn":[0.0166161254],"iteration":477,"passed_time":1.278768332,"remaining_time":1.396479224},
{"learn":[0.01654717773],"iteration":478,"passed_time":1.280935081,"remaining_time":1.393250892},
{"learn":[0.01649501026],"iteration":479,"passed_time":1.282921943,"remaining_time":1.389832105},
{"learn":[0.01642055809],"iteration":480,"passed_time":1.285061594,"remaining_time":1.386584131},
{"learn":[0.01637871265],"iteration":481,"passed_time":1.287226147,"remaining_time":1.383367519},
{"learn":[0.01632888615],"iteration":482,"passed_time":1.289356888,"remaining_time":1.380119071},
{"learn":[0.01626463234],"iteration":483,"passed_time":1.291455183,"remaining_time":1.376840649},
{"learn":[0.01619757116],"iteration":484,"passed_time":1.293583522,"remaining_time":1.373598998},
{"learn":[0.0161438331],"iteration":485,"passed_time":1.295636316,"remaining_time":1.37028203},
{"learn":[0.01609025598],"iteration":486,"passed_time":1.297939731,"remaining_time":1.367234255},
{"learn":[0.01603907198],"iteration":487,"passed_time":1.299978614,"remaining_time":1.363911988},
{"learn":[0.01600024402],"iteration":488,"passed_time":1.302191789,"remaining_time":1.360777104},
{"learn":[0.01596067399],"iteration":489,"passed_time":1.304337307,"remaining_time":1.357575564},
{"learn":[0.01592009813],"iteration":490,"passed_time":1.306334855,"remaining_time":1.354224931},
{"learn":[0.01587900817],"iteration":491,"passed_time":1.308541914,"remaining_time":1.351096123},
{"learn":[0.01582526267],"iteration":492,"passed_time":1.310689797,"remaining_time":1.347910197},
{"learn":[0.01576948762],"iteration":493,"passed_time":1.312821537,"remaining_time":1.344711938},
{"learn":[0.01571267992],"iteration":494,"passed_time":1.314830376,"remaining_time":1.341392606},
{"learn":[0.01564984918],"iteration":495,"passed_time":1.316946381,"remaining_time":1.338187452},
{"learn":[0.01559892148],"iteration":496,"passed_time":1.318999403,"remaining_time":1.334922937},
{"learn":[0.01555705816],"iteration":497,"passed_time":1.321186141,"remaining_time":1.331798078},
{"learn":[0.01552219391],"iteration":498,"passed_time":1.323440821,"remaining_time":1.328745193},
{"learn":[0.01548353136],"iteration":499,"passed_time":1.325420814,"remaining_time":1.325420814},
{"learn":[0.01542119384],"iteration":500,"passed_time":1.327674724,"remaining_time":1.322374626},
{"learn":[0.01536373943],"iteration":501,"passed_time":1.330012278,"remaining_time":1.319414571},
{"learn":[0.01532131284],"iteration":502,"passed_time":1.331805497,"remaining_time":1.31591915},
{"learn":[0.01527889669],"iteration":503,"passed_time":1.333891265,"remaining_time":1.312718388},
{"learn":[0.01524033993],"iteration":504,"passed_time":1.336116163,"remaining_time":1.309658417},
{"learn":[0.01520159841],"iteration":505,"passed_time":1.338173325,"remaining_time":1.306437989},
{"learn":[0.01515975296],"iteration":506,"passed_time":1.340251031,"remaining_time":1.303242127},
{"learn":[0.01511421949],"iteration":507,"passed_time":1.34241834,"remaining_time":1.300137448},
{"learn":[0.01506332755],"iteration":508,"passed_time":1.344596254,"remaining_time":1.297046681},
{"learn":[0.01500783563],"iteration":509,"passed_time":1.346785666,"remaining_time":1.293970542},
{"learn":[0.01496398449],"iteration":510,"passed_time":1.348885363,"remaining_time":1.29081202},
{"learn":[0.01491704583],"iteration":511,"passed_time":1.351271595,"remaining_time":1.287930739},
{"learn":[0.014872922],"iteration":512,"passed_time":1.353406375,"remaining_time":1.28481268},
{"learn":[0.01483489573],"iteration":513,"passed_time":1.355433047,"remaining_time":1.281596227},
{"learn":[0.0147971645],"iteration":514,"passed_time":1.357517809,"remaining_time":1.278439102},
{"learn":[0.01475094408],"iteration":515,"passed_time":1.359541011,"remaining_time":1.27522839},
{"learn":[0.01471097171],"iteration":516,"passed_time":1.361537067,"remaining_time":1.271996911},
{"learn":[0.01466489434],"iteration":517,"passed_time":1.363649258,"remaining_time":1.268878267},
{"learn":[0.01462364197],"iteration":518,"passed_time":1.365602098,"remaining_time":1.265615818},
{"learn":[0.01458782703],"iteration":519,"passed_time":1.367770814,"remaining_time":1.262557675},
{"learn":[0.01455079317],"iteration":520,"passed_time":1.370051939,"remaining_time":1.259606293},
{"learn":[0.01450240612],"iteration":521,"passed_time":1.372266326,"remaining_time":1.256596368},
{"learn":[0.01446897388],"iteration":522,"passed_time":1.374519187,"remaining_time":1.253624574},
{"learn":[0.01443566829],"iteration":523,"passed_time":1.37665927,"remaining_time":1.250553077},
{"learn":[0.01436996311],"iteration":524,"passed_time":1.3791502,"remaining_time":1.247802562},
{"learn":[0.01432683319],"iteration":525,"passed_time":1.381010741,"remaining_time":1.244484965},
{"learn":[0.01428244412],"iteration":526,"passed_time":1.383212044,"remaining_time":1.241478742},
{"learn":[0.01422730982],"iteration":527,"passed_time":1.385481071,"remaining_time":1.238536109},
{"learn":[0.01419217587],"iteration":528,"passed_time":1.387541836,"remaining_time":1.235410595},
{"learn":[0.01414928138],"iteration":529,"passed_time":1.389634835,"remaining_time":1.232317684},
{"learn":[0.0141043812],"iteration":530,"passed_time":1.391840539,"remaining_time":1.229328084},
{"learn":[0.01406766474],"iteration":531,"passed_time":1.393931445,"remaining_time":1.226240444},
{"learn":[0.01402762383],"iteration":532,"passed_time":1.396038959,"remaining_time":1.223171095},
{"learn":[0.01398653388],"iteration":533,"passed_time":1.398186973,"remaining_time":1.220140692},
{"learn":[0.01394099444],"iteration":534,"passed_time":1.400311029,"remaining_time":1.217092763},
{"learn":[0.01389384866],"iteration":535,"passed_time":1.402324436,"remaining_time":1.213952497},
{"learn":[0.0138545841],"iteration":536,"passed_time":1.404618808,"remaining_time":1.211058674},
{"learn":[0.01380796432],"iteration":537,"passed_time":1.40681951,"remaining_time":1.208086643},
{"learn":[0.01377257705],"iteration":538,"passed_time":1.408953582,"remaining_time":1.205060485},
{"learn":[0.01373913586],"iteration":539,"passed_time":1.41111907,"remaining_time":1.202064393},
{"learn":[0.01370714903],"iteration":540,"passed_time":1.413078028,"remaining_time":1.198896146},
{"learn":[0.01367471665],"iteration":541,"passed_time":1.415309143,"remaining_time":1.195962339},
{"learn":[0.01362049729],"iteration":542,"passed_time":1.417510234,"remaining_time":1.19300585},
{"learn":[0.01358090043],"iteration":543,"passed_time":1.419477103,"remaining_time":1.189855807},
{"learn":[0.01354605556],"iteration":544,"passed_time":1.421613945,"remaining_time":1.186852009},
{"learn":[0.01350109875],"iteration":545,"passed_time":1.423830127,"remaining_time":1.183917358},
{"learn":[0.01346367747],"iteration":546,"passed_time":1.425872928,"remaining_time":1.180841749},
{"learn":[0.01342740059],"iteration":547,"passed_time":1.428004523,"remaining_time":1.177843146},
{"learn":[0.0133980453],"iteration":548,"passed_time":1.430100139,"remaining_time":1.174818147},
{"learn":[0.01334367692],"iteration":549,"passed_time":1.432140636,"remaining_time":1.171751429},
{"learn":[0.01330403686],"iteration":550,"passed_time":1.434287445,"remaining_time":1.168775068},
{"learn":[0.01326861978],"iteration":551,"passed_time":1.43641651,"remaining_time":1.165787312},
{"learn":[0.01322718859],"iteration":552,"passed_time":1.438567873,"remaining_time":1.162820686},
{"learn":[0.01319155842],"iteration":553,"passed_time":1.440822969,"remaining_time":1.159940513},
{"learn":[0.01315702647],"iteration":554,"passed_time":1.442881124,"remaining_time":1.156904685},
{"learn":[0.01311464459],"iteration":555,"passed_time":1.44516334,"remaining_time":1.154051301},
{"learn":[0.01308377981],"iteration":556,"passed_time":1.447244747,"remaining_time":1.151040257},
{"learn":[0.01305064261],"iteration":557,"passed_time":1.449248032,"remaining_time":1.147970663},
{"learn":[0.01301940233],"iteration":558,"passed_time":1.451442471,"remaining_time":1.145055688},
{"learn":[0.01298999339],"iteration":559,"passed_time":1.453451104,"remaining_time":1.141997296},
{"learn":[0.01295644492],"iteration":560,"passed_time":1.455545423,"remaining_time":1.139009698},
{"learn":[0.01289819479],"iteration":561,"passed_time":1.457711904,"remaining_time":1.136081519},
{"learn":[0.01286194324],"iteration":562,"passed_time":1.459849088,"remaining_time":1.133133306},
{"learn":[0.0128216356],"iteration":563,"passed_time":1.46206118,"remaining_time":1.130245877},
{"learn":[0.01278394163],"iteration":564,"passed_time":1.464181698,"remaining_time":1.127290334},
{"learn":[0.01275145113],"iteration":565,"passed_time":1.466436076,"remaining_time":1.124440383},
{"learn":[0.01272335052],"iteration":566,"passed_time":1.468558624,"remaining_time":1.121491859},
{"learn":[0.01269808412],"iteration":567,"passed_time":1.470631798,"remaining_time":1.118508691},
{"learn":[0.01265373975],"iteration":568,"passed_time":1.472877128,"remaining_time":1.115659125},
{"learn":[0.01262475103],"iteration":569,"passed_time":1.47485896,"remaining_time":1.1126129},
{"learn":[0.01259965897],"iteration":570,"passed_time":1.476974136,"remaining_time":1.109670586},
{"learn":[0.01256780475],"iteration":571,"passed_time":1.479019518,"remaining_time":1.10667894},
{"learn":[0.01252909452],"iteration":572,"passed_time":1.481270766,"remaining_time":1.103844009},
{"learn":[0.01249466091],"iteration":573,"passed_time":1.483372738,"remaining_time":1.100900325},
{"learn":[0.01245398968],"iteration":574,"passed_time":1.485441584,"remaining_time":1.097935084},
{"learn":[0.01242091283],"iteration":575,"passed_time":1.487857701,"remaining_time":1.095228585},
{"learn":[0.01239365116],"iteration":576,"passed_time":1.489788011,"remaining_time":1.092166947},
{"learn":[0.01235580444],"iteration":577,"passed_time":1.491960458,"remaining_time":1.089286009},
{"learn":[0.01233158782],"iteration":578,"passed_time":1.494181058,"remaining_time":1.086442531},
{"learn":[0.01228926182],"iteration":579,"passed_time":1.496788164,"remaining_time":1.083881084},
{"learn":[0.01225494221],"iteration":580,"passed_time":1.500514035,"remaining_time":1.082126301},
{"learn":[0.0122294426],"iteration":581,"passed_time":1.503136423,"remaining_time":1.079572207},
{"learn":[0.01219934821],"iteration":582,"passed_time":1.50532837,"remaining_time":1.07671},
{"learn":[0.01217149347],"iteration":583,"passed_time":1.507207233,"remaining_time":1.07362707},
{"learn":[0.01213765368],"iteration":584,"passed_time":1.509491934,"remaining_time":1.070836158},
{"learn":[0.01210251823],"iteration":585,"passed_time":1.51148326,"remaining_time":1.067839709},
{"learn":[0.01207174957],"iteration":586,"passed_time":1.513600023,"remaining_time":1.064934939},
{"learn":[0.01203543991],"iteration":587,"passed_time":1.515919835,"remaining_time":1.062175122},
{"learn":[0.01200381666],"iteration":588,"passed_time":1.51793941,"remaining_time":1.059207297},
{"learn":[0.01196382642],"iteration":589,"passed_time":1.519565543,"remaining_time":1.055969276},
{"learn":[0.01193153486],"iteration":590,"passed_time":1.521711348,"remaining_time":1.053096347},
{"learn":[0.0118977204],"iteration":591,"passed_time":1.523925093,"remaining_time":1.050272699},
{"learn":[0.01187535301],"iteration":592,"passed_time":1.526214693,"remaining_time":1.047503171},
{"learn":[0.01185010374],"iteration":593,"passed_time":1.528301721,"remaining_time":1.044596799},
{"learn":[0.01181199104],"iteration":594,"passed_time":1.530443951,"remaining_time":1.041730756},
{"learn":[0.01177906096],"iteration":595,"passed_time":1.532647972,"remaining_time":1.038909028},
{"learn":[0.01174331456],"iteration":596,"passed_time":1.534615486,"remaining_time":1.035929717},
{"learn":[0.01170835793],"iteration":597,"passed_time":1.536780664,"remaining_time":1.033086667},
{"learn":[0.01167595014],"iteration":598,"passed_time":1.538891618,"remaining_time":1.030209581},
{"learn":[0.01165197045],"iteration":599,"passed_time":1.541014402,"remaining_time":1.027342935},
{"learn":[0.01161447316],"iteration":600,"passed_time":1.543078412,"remaining_time":1.024439745},
{"learn":[0.01157956943],"iteration":601,"passed_time":1.545192998,"remaining_time":1.02157278},
{"learn":[0.01155493408],"iteration":602,"passed_time":1.547400068,"remaining_time":1.018769199},
{"learn":[0.01153258011],"iteration":603,"passed_time":1.549506106,"remaining_time":1.015901354},
{"learn":[0.01149877831],"iteration":604,"passed_time":1.551550606,"remaining_time":1.012995851},
{"learn":[0.01147625893],"iteration":605,"passed_time":1.553704952,"remaining_time":1.010164606},
{"learn":[0.01145398915],"iteration":606,"passed_time":1.555759928,"remaining_time":1.007271255},
{"learn":[0.01141491011],"iteration":607,"passed_time":1.558005049,"remaining_time":1.004503255},
{"learn":[0.01137480587],"iteration":608,"passed_time":1.560111861,"remaining_time":1.001648174},
{"learn":[0.01134740412],"iteration":609,"passed_time":1.562233498,"remaining_time":0.9988050233},
{"learn":[0.01131027862],"iteration":610,"passed_time":1.564370927,"remaining_time":0.9959742888},
{"learn":[0.01128305048],"iteration":611,"passed_time":1.566586119,"remaining_time":0.9931951213},
{"learn":[0.01125119478],"iteration":612,"passed_time":1.568634783,"remaining_time":0.9903126607},
{"learn":[0.01122529358],"iteration":613,"passed_time":1.57088946,"remaining_time":0.9875624295},
{"learn":[0.01118416786],"iteration":614,"passed_time":1.573135133,"remaining_time":0.9848081724},
{"learn":[0.01115397811],"iteration":615,"passed_time":1.574996476,"remaining_time":0.9818159852},
{"learn":[0.01111863852],"iteration":616,"passed_time":1.577288401,"remaining_time":0.9790947449},
{"learn":[0.01109357625],"iteration":617,"passed_time":1.579367,"remaining_time":0.9762430325},
{"learn":[0.01106599644],"iteration":618,"passed_time":1.581653915,"remaining_time":0.9735220381},
{"learn":[0.01104363352],"iteration":619,"passed_time":1.583662964,"remaining_time":0.9706321391},
{"learn":[0.01101837307],"iteration":620,"passed_time":1.585833311,"remaining_time":0.967843518},
{"learn":[0.01099354029],"iteration":621,"passed_time":1.588001551,"remaining_time":0.9650556047},
{"learn":[0.01095725298],"iteration":622,"passed_time":1.590055637,"remaining_time":0.9622006021},
{"learn":[0.01093849689],"iteration":623,"passed_time":1.592646206,"remaining_time":0.959671432},
{"learn":[0.0109087348],"iteration":624,"passed_time":1.594595759,"remaining_time":0.9567574554},
{"learn":[0.01087692827],"iteration":625,"passed_time":1.596672115,"remaining_time":0.9539223178},
{"learn":[0.01085196286],"iteration":626,"passed_time":1.598748026,"remaining_time":0.9510893359},
{"learn":[0.01082853824],"iteration":627,"passed_time":1.6008971,"remaining_time":0.9483021036},
{"learn":[0.01080716103],"iteration":628,"passed_time":1.602927332,"remaining_time":0.9454468048},
{"learn":[0.01077446491],"iteration":629,"passed_time":1.605077826,"remaining_time":0.9426647549},
{"learn":[0.01074853614],"iteration":630,"passed_time":1.607221782,"remaining_time":0.9398808838},
{"learn":[0.01071071029],"iteration":631,"passed_time":1.609272954,"remaining_time":0.9370450114},
{"learn":[0.01069024503],"iteration":632,"passed_time":1.611382448,"remaining_time":0.9342454321},
{"learn":[0.01066265553],"iteration":633,"passed_time":1.613415822,"remaining_time":0.9314040864},
{"learn":[0.0106354028],"iteration":634,"passed_time":1.615675236,"remaining_time":0.9286952144},
{"learn":[0.01061740965],"iteration":635,"passed_time":1.617770263,"remaining_time":0.9258936725},
{"learn":[0.0105908826],"iteration":636,"passed_time":1.619780184,"remaining_time":0.9230458507},
{"learn":[0.01055887789],"iteration":637,"passed_time":1.621986103,"remaining_time":0.9203118638},
{"learn":[0.0105334729],"iteration":638,"passed_time":1.624063462,"remaining_time":0.9175069009},
{"learn":[0.01050345898],"iteration":639,"passed_time":1.626084619,"remaining_time":0.9146725983},
{"learn":[0.01048220843],"iteration":640,"passed_time":1.628271775,"remaining_time":0.9119338024},
{"learn":[0.01046191603],"iteration":641,"passed_time":1.630364318,"remaining_time":0.9091439656},
{"learn":[0.01043611988],"iteration":642,"passed_time":1.632663257,"remaining_time":0.9064708909},
{"learn":[0.01040876284],"iteration":643,"passed_time":1.634863599,"remaining_time":0.9037444738},
{"learn":[0.01038518101],"iteration":644,"passed_time":1.637142945,"remaining_time":0.9010631712},
{"learn":[0.01036087126],"iteration":645,"passed_time":1.639312973,"remaining_time":0.8983232083},
{"learn":[0.01034078598],"iteration":646,"passed_time":1.641433434,"remaining_time":0.8955579633},
{"learn":[0.01031531692],"iteration":647,"passed_time":1.643602268,"remaining_time":0.8928209849},
{"learn":[0.01028618887],"iteration":648,"passed_time":1.645670447,"remaining_time":0.8900313206},
{"learn":[0.0102665998],"iteration":649,"passed_time":1.647741774,"remaining_time":0.8872455707},
{"learn":[0.01023838818],"iteration":650,"passed_time":1.649887404,"remaining_time":0.8845018493},
{"learn":[0.01022477746],"iteration":651,"passed_time":1.651997041,"remaining_time":0.881740752},
{"learn":[0.01020163968],"iteration":652,"passed_time":1.65417166,"remaining_time":0.8790161809},
{"learn":[0.01017812043],"iteration":653,"passed_time":1.656342015,"remaining_time":0.8762910352},
{"learn":[0.01015827432],"iteration":654,"passed_time":1.658349267,"remaining_time":0.8734816748},
{"learn":[0.01014179438],"iteration":655,"passed_time":1.660441917,"remaining_time":0.8707195419},
{"learn":[0.01012575626],"iteration":656,"passed_time":1.662482381,"remaining_time":0.8679322022},
{"learn":[0.01010102481],"iteration":657,"passed_time":1.664774025,"remaining_time":0.8652776845},
{"learn":[0.01006910652],"iteration":658,"passed_time":1.666966457,"remaining_time":0.8625729313},
{"learn":[0.01004985422],"iteration":659,"passed_time":1.669021294,"remaining_time":0.8597988483},
{"learn":[0.01003147662],"iteration":660,"passed_time":1.671165914,"remaining_time":0.8570729878},
{"learn":[0.01000736803],"iteration":661,"passed_time":1.673254868,"remaining_time":0.8543204612},
{"learn":[0.009981925786],"iteration":662,"passed_time":1.675608272,"remaining_time":0.8517043555},
{"learn":[0.009955060482],"iteration":663,"passed_time":1.677916075,"remaining_time":0.8490659655},
{"learn":[0.009933821857],"iteration":664,"passed_time":1.680063525,"remaining_time":0.8463477909},
{"learn":[0.009912233055],"iteration":665,"passed_time":1.682241058,"remaining_time":0.8436464164},
{"learn":[0.009891162813],"iteration":666,"passed_time":1.684124981,"remaining_time":0.840800028},
{"learn":[0.009870652854],"iteration":667,"passed_time":1.686182472,"remaining_time":0.8380427857},
{"learn":[0.009847989678],"iteration":668,"passed_time":1.688322288,"remaining_time":0.8353283666},
{"learn":[0.009822524339],"iteration":669,"passed_time":1.690368311,"remaining_time":0.8325694669},
{"learn":[0.009802520275],"iteration":670,"passed_time":1.692521162,"remaining_time":0.8298650705},
{"learn":[0.009784707427],"iteration":671,"passed_time":1.694610802,"remaining_time":0.8271314627},
{"learn":[0.009762704372],"iteration":672,"passed_time":1.696823857,"remaining_time":0.8244597342},
{"learn":[0.009737756848],"iteration":673,"passed_time":1.699175143,"remaining_time":0.8218562265},
{"learn":[0.009702649713],"iteration":674,"passed_time":1.701133086,"remaining_time":0.8190640785},
{"learn":[0.009675736725],"iteration":675,"passed_time":1.703137935,"remaining_time":0.81629688},
{"learn":[0.009654071927],"iteration":676,"passed_time":1.705164709,"remaining_time":0.8135423944},
{"learn":[0.009634193033],"iteration":677,"passed_time":1.707264624,"remaining_time":0.8108247922},
{"learn":[0.009604091942],"iteration":678,"passed_time":1.70933267,"remaining_time":0.8080939428},
{"learn":[0.009587725997],"iteration":679,"passed_time":1.711417419,"remaining_time":0.8053729029},
{"learn":[0.009561504424],"iteration":680,"passed_time":1.713661623,"remaining_time":0.8027284253},
{"learn":[0.009537582099],"iteration":681,"passed_time":1.715733856,"remaining_time":0.8000049358},
{"learn":[0.009509988129],"iteration":682,"passed_time":1.717790811,"remaining_time":0.797276262},
{"learn":[0.009487393498],"iteration":683,"passed_time":1.719934402,"remaining_time":0.7945895775},
{"learn":[0.009461954236],"iteration":684,"passed_time":1.722119218,"remaining_time":0.7919234361},
{"learn":[0.00943608582],"iteration":685,"passed_time":1.724416427,"remaining_time":0.789310143},
{"learn":[0.009414935112],"iteration":686,"passed_time":1.726400645,"remaining_time":0.78655517},
{"learn":[0.009384983778],"iteration":687,"passed_time":1.728454656,"remaining_time":0.7838340882},
{"learn":[0.00936602056],"iteration":688,"passed_time":1.730553494,"remaining_time":0.7811351765},
{"learn":[0.00934054777],"iteration":689,"passed_time":1.732647219,"remaining_time":0.7784357072},
{"learn":[0.009323453903],"iteration":690,"passed_time":1.734699621,"remaining_time":0.7757195119},
{"learn":[0.009295357764],"iteration":691,"passed_time":1.736811449,"remaining_time":0.7730316853},
{"learn":[0.009274762124],"iteration":692,"passed_time":1.739002919,"remaining_time":0.7703808026},
{"learn":[0.009251002967],"iteration":693,"passed_time":1.741200093,"remaining_time":0.7677337586},
{"learn":[0.00923396498],"iteration":694,"passed_time":1.743320824,"remaining_time":0.7650544623},
{"learn":[0.009210632741],"iteration":695,"passed_time":1.745475131,"remaining_time":0.7623914366},
{"learn":[0.009194910526],"iteration":696,"passed_time":1.747479107,"remaining_time":0.7596645184},
{"learn":[0.009177242219],"iteration":697,"passed_time":1.749598135,"remaining_time":0.7569894509},
{"learn":[0.009157238901],"iteration":698,"passed_time":1.751909408,"remaining_time":0.7543987578},
{"learn":[0.009136653692],"iteration":699,"passed_time":1.754011282,"remaining_time":0.751719121},
{"learn":[0.009121739864],"iteration":700,"passed_time":1.756155184,"remaining_time":0.7490590587},
{"learn":[0.009102725238],"iteration":701,"passed_time":1.758286045,"remaining_time":0.7463949309},
{"learn":[0.00908222869],"iteration":702,"passed_time":1.760411875,"remaining_time":0.7437301949},
{"learn":[0.009064696729],"iteration":703,"passed_time":1.762509669,"remaining_time":0.7410552018},
{"learn":[0.009037485719],"iteration":704,"passed_time":1.764505056,"remaining_time":0.7383389951},
{"learn":[0.00901806578],"iteration":705,"passed_time":1.766754312,"remaining_time":0.7357305491},
{"learn":[0.009004202485],"iteration":706,"passed_time":1.769038492,"remaining_time":0.733137593},
{"learn":[0.008989997208],"iteration":707,"passed_time":1.771172848,"remaining_time":0.7304837168},
{"learn":[0.0089720577],"iteration":708,"passed_time":1.773514849,"remaining_time":0.7279165318},
{"learn":[0.008952015638],"iteration":709,"passed_time":1.775640287,"remaining_time":0.7252615255},
{"learn":[0.008933638036],"iteration":710,"passed_time":1.777698768,"remaining_time":0.7225807932},
{"learn":[0.008910863101],"iteration":711,"passed_time":1.779838294,"remaining_time":0.7199345909},
{"learn":[0.008891629428],"iteration":712,"passed_time":1.782105055,"remaining_time":0.717341025},
{"learn":[0.008861540258],"iteration":713,"passed_time":1.784272675,"remaining_time":0.7147086626},
{"learn":[0.00884225145],"iteration":714,"passed_time":1.786448609,"remaining_time":0.712080914},
{"learn":[0.008823060244],"iteration":715,"passed_time":1.788596496,"remaining_time":0.7094433028},
{"learn":[0.008806547523],"iteration":716,"passed_time":1.790636654,"remaining_time":0.7067645369},
{"learn":[0.008786794543],"iteration":717,"passed_time":1.792946456,"remaining_time":0.704193455},
{"learn":[0.008769863099],"iteration":718,"passed_time":1.794836649,"remaining_time":0.7014591075},
{"learn":[0.008748324215],"iteration":719,"passed_time":1.797134656,"remaining_time":0.6988856996},
{"learn":[0.008724541962],"iteration":720,"passed_time":1.799213516,"remaining_time":0.6962282538},
{"learn":[0.008710029721],"iteration":721,"passed_time":1.801308087,"remaining_time":0.6935784599},
{"learn":[0.008689810336],"iteration":722,"passed_time":1.803580561,"remaining_time":0.6909983615},
{"learn":[0.0086750485],"iteration":723,"passed_time":1.805682787,"remaining_time":0.6883542118},
{"learn":[0.008657513559],"iteration":724,"passed_time":1.807857154,"remaining_time":0.6857389205},
{"learn":[0.008638460189],"iteration":725,"passed_time":1.810008886,"remaining_time":0.6831163015},
{"learn":[0.00862018317],"iteration":726,"passed_time":1.81197911,"remaining_time":0.6804268186},
{"learn":[0.008598408103],"iteration":727,"passed_time":1.81406677,"remaining_time":0.6777831887},
{"learn":[0.008577516675],"iteration":728,"passed_time":1.816158552,"remaining_time":0.6751426166},
{"learn":[0.008556355536],"iteration":729,"passed_time":1.818342099,"remaining_time":0.6725374886},
{"learn":[0.008534358442],"iteration":730,"passed_time":1.820510735,"remaining_time":0.6699280271},
{"learn":[0.008517938852],"iteration":731,"passed_time":1.822880809,"remaining_time":0.6673935203},
{"learn":[0.008501831442],"iteration":732,"passed_time":1.824918048,"remaining_time":0.664738225},
{"learn":[0.008480280638],"iteration":733,"passed_time":1.826928983,"remaining_time":0.6620750811},
{"learn":[0.008462814242],"iteration":734,"passed_time":1.829029886,"remaining_time":0.6594461494},
{"learn":[0.008443726599],"iteration":735,"passed_time":1.831940525,"remaining_time":0.6571091012},
{"learn":[0.008435070515],"iteration":736,"passed_time":1.834789174,"remaining_time":0.6547483757},
{"learn":[0.0084207654],"iteration":737,"passed_time":1.83723395,"remaining_time":0.6522429471},
{"learn":[0.008406786621],"iteration":738,"passed_time":1.839660029,"remaining_time":0.6497310793},
{"learn":[0.008390937001],"iteration":739,"passed_time":1.842036711,"remaining_time":0.6472020875},
{"learn":[0.008371394873],"iteration":740,"passed_time":1.844242367,"remaining_time":0.6446137288},
{"learn":[0.00835300982],"iteration":741,"passed_time":1.846446003,"remaining_time":0.6420256991},
{"learn":[0.008334821463],"iteration":742,"passed_time":1.848715341,"remaining_time":0.6394614303},
{"learn":[0.008313559741],"iteration":743,"passed_time":1.85097748,"remaining_time":0.6368954769},
{"learn":[0.008296357095],"iteration":744,"passed_time":1.853223156,"remaining_time":0.6343247044},
{"learn":[0.008279581368],"iteration":745,"passed_time":1.855314317,"remaining_time":0.6317021938},
{"learn":[0.008266254514],"iteration":746,"passed_time":1.857388893,"remaining_time":0.6290754886},
{"learn":[0.008248740435],"iteration":747,"passed_time":1.859765764,"remaining_time":0.6265521024},
{"learn":[0.008231524378],"iteration":748,"passed_time":1.862287264,"remaining_time":0.6240775745},
{"learn":[0.008214371651],"iteration":749,"passed_time":1.864805686,"remaining_time":0.6216018955},
{"learn":[0.008199596405],"iteration":750,"passed_time":1.867002996,"remaining_time":0.6190196352},
{"learn":[0.00818085745],"iteration":751,"passed_time":1.869427034,"remaining_time":0.6165131708},
{"learn":[0.008160738647],"iteration":752,"passed_time":1.871526693,"remaining_time":0.6139005221},
{"learn":[0.008146575093],"iteration":753,"passed_time":1.873791579,"remaining_time":0.6113431411},
{"learn":[0.008129554987],"iteration":754,"passed_time":1.875877064,"remaining_time":0.6087283188},
{"learn":[0.00811624676],"iteration":755,"passed_time":1.877922581,"remaining_time":0.6061019971},
{"learn":[0.00809455812],"iteration":756,"passed_time":1.879994595,"remaining_time":0.6034857155},
{"learn":[0.008075815439],"iteration":757,"passed_time":1.882365898,"remaining_time":0.6009664213},
{"learn":[0.008055108041],"iteration":758,"passed_time":1.884662635,"remaining_time":0.5984238405},
{"learn":[0.008036915213],"iteration":759,"passed_time":1.886843455,"remaining_time":0.5958453015},
{"learn":[0.00802103132],"iteration":760,"passed_time":1.888971162,"remaining_time":0.5932511272},
{"learn":[0.008000095934],"iteration":761,"passed_time":1.891061014,"remaining_time":0.5906463536},
{"learn":[0.007984699309],"iteration":762,"passed_time":1.893107169,"remaining_time":0.5880293565},
{"learn":[0.00796584785],"iteration":763,"passed_time":1.895155004,"remaining_time":0.5854143731},
{"learn":[0.007947851717],"iteration":764,"passed_time":1.897343808,"remaining_time":0.5828441763},
{"learn":[0.007931426167],"iteration":765,"passed_time":1.899486504,"remaining_time":0.5802608903},
{"learn":[0.007913714647],"iteration":766,"passed_time":1.901585481,"remaining_time":0.5776654719},
{"learn":[0.007890997827],"iteration":767,"passed_time":1.903670796,"remaining_time":0.5750672196},
{"learn":[0.007877904177],"iteration":768,"passed_time":1.905813587,"remaining_time":0.5724875664},
{"learn":[0.007864320278],"iteration":769,"passed_time":1.908007169,"remaining_time":0.5699242194},
{"learn":[0.007851174474],"iteration":770,"passed_time":1.90991573,"remaining_time":0.5672771752},
{"learn":[0.007830886543],"iteration":771,"passed_time":1.912068792,"remaining_time":0.5647042546},
{"learn":[0.007819218934],"iteration":772,"passed_time":1.914355461,"remaining_time":0.5621716556},
{"learn":[0.007802519202],"iteration":773,"passed_time":1.91670747,"remaining_time":0.5596587703},
{"learn":[0.007789173722],"iteration":774,"passed_time":1.918656562,"remaining_time":0.5570293244},
{"learn":[0.007773780823],"iteration":775,"passed_time":1.920838783,"remaining_time":0.554468927},
{"learn":[0.007756616175],"iteration":776,"passed_time":1.922820455,"remaining_time":0.5518519454},
{"learn":[0.007736468315],"iteration":777,"passed_time":1.924992702,"remaining_time":0.5492909767},
{"learn":[0.007721850276],"iteration":778,"passed_time":1.927280295,"remaining_time":0.5467637294},
{"learn":[0.007701189071],"iteration":779,"passed_time":1.929375571,"remaining_time":0.5441828535},
{"learn":[0.007688707858],"iteration":780,"passed_time":1.931407498,"remaining_time":0.5415854572},
{"learn":[0.007675170898],"iteration":781,"passed_time":1.933527679,"remaining_time":0.53901411},
{"learn":[0.00765716061],"iteration":782,"passed_time":1.935611248,"remaining_time":0.5364337687},
{"learn":[0.007644898444],"iteration":783,"passed_time":1.937633781,"remaining_time":0.5338378784},
{"learn":[0.007634043694],"iteration":784,"passed_time":1.939890628,"remaining_time":0.5313076243},
{"learn":[0.007624325156],"iteration":785,"passed_time":1.941945919,"remaining_time":0.5287231891},
{"learn":[0.007612109184],"iteration":786,"passed_time":1.944231557,"remaining_time":0.5262024416},
{"learn":[0.007598119974],"iteration":787,"passed_time":1.946351908,"remaining_time":0.5236378231},
{"learn":[0.007574950904],"iteration":788,"passed_time":1.948574988,"remaining_time":0.5211018028},
{"learn":[0.007561099529],"iteration":789,"passed_time":1.950610032,"remaining_time":0.5185165908},
{"learn":[0.007546611875],"iteration":790,"passed_time":1.952694919,"remaining_time":0.5159459394},
{"learn":[0.007529573143],"iteration":791,"passed_time":1.954880049,"remaining_time":0.5134028412},
{"learn":[0.007512135059],"iteration":792,"passed_time":1.956932806,"remaining_time":0.5108260919},
{"learn":[0.007497088611],"iteration":793,"passed_time":1.959013479,"remaining_time":0.5082579051},
{"learn":[0.00748243928],"iteration":794,"passed_time":1.961142089,"remaining_time":0.505703306},
{"learn":[0.007469309866],"iteration":795,"passed_time":1.963160096,"remaining_time":0.5031214317},
{"learn":[0.007457645237],"iteration":796,"passed_time":1.965280621,"remaining_time":0.5005670843},
{"learn":[0.007441949844],"iteration":797,"passed_time":1.967478699,"remaining_time":0.4980334553},
{"learn":[0.007429616153],"iteration":798,"passed_time":1.969601032,"remaining_time":0.4954816113},
{"learn":[0.007418783754],"iteration":799,"passed_time":1.971658154,"remaining_time":0.4929145386},
{"learn":[0.007406913489],"iteration":800,"passed_time":1.973806451,"remaining_time":0.4903713903},
{"learn":[0.007395003736],"iteration":801,"passed_time":1.976020221,"remaining_time":0.4878453911},
{"learn":[0.007379361987],"iteration":802,"passed_time":1.978208423,"remaining_time":0.485313897},
{"learn":[0.007364329696],"iteration":803,"passed_time":1.980313151,"remaining_time":0.4827629074},
{"learn":[0.007354172319],"iteration":804,"passed_time":1.982475849,"remaining_time":0.480227069},
{"learn":[0.007339087129],"iteration":805,"passed_time":1.984626227,"remaining_time":0.4776891911},
{"learn":[0.00732447356],"iteration":806,"passed_time":1.98669985,"remaining_time":0.4751339169},
{"learn":[0.007312528044],"iteration":807,"passed_time":1.988717353,"remaining_time":0.4725664996},
{"learn":[0.007302891463],"iteration":808,"passed_time":1.991003439,"remaining_time":0.4700638527},
{"learn":[0.007287693024],"iteration":809,"passed_time":1.993060045,"remaining_time":0.4675079117},
{"learn":[0.007276888937],"iteration":810,"passed_time":1.995146283,"remaining_time":0.4649601079},
{"learn":[0.007258267701],"iteration":811,"passed_time":1.997319567,"remaining_time":0.4624335942},
{"learn":[0.00724529475],"iteration":812,"passed_time":1.999547367,"remaining_time":0.4599204891},
{"learn":[0.007231779397],"iteration":813,"passed_time":2.001852107,"remaining_time":0.4574256657},
{"learn":[0.007215167582],"iteration":814,"passed_time":2.003848694,"remaining_time":0.4548613599},
{"learn":[0.007199815661],"iteration":815,"passed_time":2.005978012,"remaining_time":0.4523283753},
{"learn":[0.007186517119],"iteration":816,"passed_time":2.008001786,"remaining_time":0.449772738},
{"learn":[0.007168265432],"iteration":817,"passed_time":2.010100951,"remaining_time":0.4472351749},
{"learn":[0.00715772137],"iteration":818,"passed_time":2.012113684,"remaining_time":0.444679581},
{"learn":[0.007143646479],"iteration":819,"passed_time":2.014360641,"remaining_time":0.442176726},
{"learn":[0.007131260633],"iteration":820,"passed_time":2.01637597,"remaining_time":0.4396239935},
{"learn":[0.007121858001],"iteration":821,"passed_time":2.01869119,"remaining_time":0.4371375084},
{"learn":[0.007108293474],"iteration":822,"passed_time":2.020818951,"remaining_time":0.434611123},
{"learn":[0.007094812393],"iteration":823,"passed_time":2.022942507,"remaining_time":0.4320848072},
{"learn":[0.007082559913],"iteration":824,"passed_time":2.025128043,"remaining_time":0.4295726151},
{"learn":[0.007068171352],"iteration":825,"passed_time":2.027299249,"remaining_time":0.4270581952},
{"learn":[0.007056239247],"iteration":826,"passed_time":2.029378267,"remaining_time":0.4245253207},
{"learn":[0.007045936584],"iteration":827,"passed_time":2.031520922,"remaining_time":0.4220067615},
{"learn":[0.00702740252],"iteration":828,"passed_time":2.033626411,"remaining_time":0.4194814429},
{"learn":[0.007014398277],"iteration":829,"passed_time":2.035792953,"remaining_time":0.416969641},
{"learn":[0.006996569782],"iteration":830,"passed_time":2.038012613,"remaining_time":0.4144694725},
{"learn":[0.006982216239],"iteration":831,"passed_time":2.040056123,"remaining_time":0.4119344094},
{"learn":[0.006969001889],"iteration":832,"passed_time":2.042156978,"remaining_time":0.4094120232},
{"learn":[0.006958069652],"iteration":833,"passed_time":2.044482439,"remaining_time":0.4069353536},
{"learn":[0.006943805516],"iteration":834,"passed_time":2.046623733,"remaining_time":0.4044226538},
{"learn":[0.006933066994],"iteration":835,"passed_time":2.048837956,"remaining_time":0.4019251492},
{"learn":[0.006921349466],"iteration":836,"passed_time":2.051163768,"remaining_time":0.3994500529},
{"learn":[0.006909584999],"iteration":837,"passed_time":2.053126353,"remaining_time":0.3969050945},
{"learn":[0.00690009892],"iteration":838,"passed_time":2.055170423,"remaining_time":0.3943771611},
{"learn":[0.006890030205],"iteration":839,"passed_time":2.057253794,"remaining_time":0.3918578656},
{"learn":[0.006873670965],"iteration":840,"passed_time":2.059307671,"remaining_time":0.3893340305},
{"learn":[0.006858339906],"iteration":841,"passed_time":2.061582493,"remaining_time":0.3868527718},
{"learn":[0.006848104298],"iteration":842,"passed_time":2.063637559,"remaining_time":0.3843310756},
{"learn":[0.006834715605],"iteration":843,"passed_time":2.065784121,"remaining_time":0.3818273968},
{"learn":[0.006817792356],"iteration":844,"passed_time":2.067889792,"remaining_time":0.3793170624},
{"learn":[0.006807050109],"iteration":845,"passed_time":2.069955457,"remaining_time":0.3768004023},
{"learn":[0.006794810295],"iteration":846,"passed_time":2.072463726,"remaining_time":0.3743647581},
{"learn":[0.006780800223],"iteration":847,"passed_time":2.074688188,"remaining_time":0.3718780714},
{"learn":[0.006765301526],"iteration":848,"passed_time":2.076832737,"remaining_time":0.3693777895},
{"learn":[0.00675264746],"iteration":849,"passed_time":2.078957663,"remaining_time":0.3668748816},
{"learn":[0.006737537682],"iteration":850,"passed_time":2.081211239,"remaining_time":0.3643953874},
{"learn":[0.006723260134],"iteration":851,"passed_time":2.083223584,"remaining_time":0.3618745193},
{"learn":[0.006707977504],"iteration":852,"passed_time":2.085547137,"remaining_time":0.3594084749},
{"learn":[0.006693519652],"iteration":853,"passed_time":2.08770241,"remaining_time":0.3569139951},
{"learn":[0.006682698429],"iteration":854,"passed_time":2.089804149,"remaining_time":0.3544112299},
{"learn":[0.006672012061],"iteration":855,"passed_time":2.092073911,"remaining_time":0.3519376674},
{"learn":[0.006661572307],"iteration":856,"passed_time":2.094431882,"remaining_time":0.3494792989},
{"learn":[0.006645330787],"iteration":857,"passed_time":2.096849429,"remaining_time":0.3470310243},
{"learn":[0.00663600713],"iteration":858,"passed_time":2.099039492,"remaining_time":0.3445454812},
{"learn":[0.006621833891],"iteration":859,"passed_time":2.101278201,"remaining_time":0.3420685444},
{"learn":[0.006605756283],"iteration":860,"passed_time":2.103531143,"remaining_time":0.3395944586},
{"learn":[0.006594251841],"iteration":861,"passed_time":2.105919738,"remaining_time":0.337142603},
{"learn":[0.006585267186],"iteration":862,"passed_time":2.108174488,"remaining_time":0.3346696465},
{"learn":[0.006573823094],"iteration":863,"passed_time":2.110500438,"remaining_time":0.3322084023},
{"learn":[0.006563457847],"iteration":864,"passed_time":2.113137865,"remaining_time":0.329796083},
{"learn":[0.006554494798],"iteration":865,"passed_time":2.115272803,"remaining_time":0.3273054914},
{"learn":[0.00653732717],"iteration":866,"passed_time":2.117711848,"remaining_time":0.3248623711},
{"learn":[0.006527314335],"iteration":867,"passed_time":2.119969598,"remaining_time":0.32239169},
{"learn":[0.006516352296],"iteration":868,"passed_time":2.122419981,"remaining_time":0.319950538},
{"learn":[0.006506267935],"iteration":869,"passed_time":2.124771515,"remaining_time":0.3174945942},
{"learn":[0.006496612728],"iteration":870,"passed_time":2.126858755,"remaining_time":0.3149997467},
{"learn":[0.006486894935],"iteration":871,"passed_time":2.129017229,"remaining_time":0.3125162906},
{"learn":[0.006467816979],"iteration":872,"passed_time":2.131229059,"remaining_time":0.3100413407},
{"learn":[0.006455241144],"iteration":873,"passed_time":2.133435719,"remaining_time":0.3075662478},
{"learn":[0.006443439424],"iteration":874,"passed_time":2.135631354,"remaining_time":0.3050901934},
{"learn":[0.006432065368],"iteration":875,"passed_time":2.137616112,"remaining_time":0.3025849292},
{"learn":[0.006420685351],"iteration":876,"passed_time":2.139638507,"remaining_time":0.3000861305},
{"learn":[0.006410162151],"iteration":877,"passed_time":2.141735094,"remaining_time":0.2975987261},
{"learn":[0.006397812068],"iteration":878,"passed_time":2.143917425,"remaining_time":0.2951240141},
{"learn":[0.006384930015],"iteration":879,"passed_time":2.146066499,"remaining_time":0.2926454316},
{"learn":[0.006373105943],"iteration":880,"passed_time":2.148279539,"remaining_time":0.2901762373},
{"learn":[0.006360358745],"iteration":881,"passed_time":2.150451156,"remaining_time":0.2877020821},
{"learn":[0.006350262463],"iteration":882,"passed_time":2.152570605,"remaining_time":0.2852216997},
{"learn":[0.006338574737],"iteration":883,"passed_time":2.154864429,"remaining_time":0.2827650156},
{"learn":[0.006324848533],"iteration":884,"passed_time":2.156759944,"remaining_time":0.2802569419},
{"learn":[0.006313379109],"iteration":885,"passed_time":2.15881854,"remaining_time":0.2777712343},
{"learn":[0.006302215159],"iteration":886,"passed_time":2.160961532,"remaining_time":0.2752972414},
{"learn":[0.006290898472],"iteration":887,"passed_time":2.163012361,"remaining_time":0.2728123698},
{"learn":[0.00628067255],"iteration":888,"passed_time":2.16532355,"remaining_time":0.2703609832},
{"learn":[0.006271450222],"iteration":889,"passed_time":2.167606746,"remaining_time":0.2679064518},
{"learn":[0.006262719631],"iteration":890,"passed_time":2.169535608,"remaining_time":0.2654089576},
{"learn":[0.006252489239],"iteration":891,"passed_time":2.171668825,"remaining_time":0.262937481},
{"learn":[0.006241892651],"iteration":892,"passed_time":2.17372937,"remaining_time":0.2604580545},
{"learn":[0.00622895062],"iteration":893,"passed_time":2.17591268,"remaining_time":0.2579941209},
{"learn":[0.00621951744],"iteration":894,"passed_time":2.177900091,"remaining_time":0.2555078319},
{"learn":[0.006207082793],"iteration":895,"passed_time":2.179895964,"remaining_time":0.2530236386},
{"learn":[0.006197757274],"iteration":896,"passed_time":2.182098993,"remaining_time":0.2505643213},
{"learn":[0.006185243279],"iteration":897,"passed_time":2.184318468,"remaining_time":0.2481074429},
{"learn":[0.006177596375],"iteration":898,"passed_time":2.186475633,"remaining_time":0.2456440922},
{"learn":[0.006165731326],"iteration":899,"passed_time":2.188499859,"remaining_time":0.243166651},
{"learn":[0.006156075746],"iteration":900,"passed_time":2.190635264,"remaining_time":0.2407024319},
{"learn":[0.00614887774],"iteration":901,"passed_time":2.193021609,"remaining_time":0.2382662059},
{"learn":[0.006138791144],"iteration":902,"passed_time":2.195072964,"remaining_time":0.2357941058},
{"learn":[0.00612763539],"iteration":903,"passed_time":2.197222416,"remaining_time":0.2333333539},
{"learn":[0.006116836518],"iteration":904,"passed_time":2.199458263,"remaining_time":0.2308823591},
{"learn":[0.00610678643],"iteration":905,"passed_time":2.201661127,"remaining_time":0.2284284172},
{"learn":[0.006096587703],"iteration":906,"passed_time":2.203821384,"remaining_time":0.2259706601},
{"learn":[0.006085637584],"iteration":907,"passed_time":2.205893316,"remaining_time":0.2235046091},
{"learn":[0.006075532734],"iteration":908,"passed_time":2.208094272,"remaining_time":0.2210523418},
{"learn":[0.006065716222],"iteration":909,"passed_time":2.210089325,"remaining_time":0.2185802629},
{"learn":[0.00605623275],"iteration":910,"passed_time":2.212186547,"remaining_time":0.2161192126},
{"learn":[0.006046108156],"iteration":911,"passed_time":2.214311494,"remaining_time":0.2136616354},
{"learn":[0.006038270146],"iteration":912,"passed_time":2.216291637,"remaining_time":0.2111909884},
{"learn":[0.006028517708],"iteration":913,"passed_time":2.218463529,"remaining_time":0.2087394568},
{"learn":[0.006018796563],"iteration":914,"passed_time":2.220749272,"remaining_time":0.2062991127},
{"learn":[0.006008184701],"iteration":915,"passed_time":2.222866894,"remaining_time":0.203843689},
{"learn":[0.005997981876],"iteration":916,"passed_time":2.225167566,"remaining_time":0.2014055703},
{"learn":[0.005985879526],"iteration":917,"passed_time":2.227350187,"remaining_time":0.1989572062},
{"learn":[0.005977983773],"iteration":918,"passed_time":2.229555917,"remaining_time":0.1965114574},
{"learn":[0.005962977558],"iteration":919,"passed_time":2.231465277,"remaining_time":0.1940404589},
{"learn":[0.005953512341],"iteration":920,"passed_time":2.233649828,"remaining_time":0.1915942849},
{"learn":[0.005944287404],"iteration":921,"passed_time":2.235596818,"remaining_time":0.1891285812},
{"learn":[0.005933603644],"iteration":922,"passed_time":2.237919311,"remaining_time":0.1866953271},
{"learn":[0.005923999101],"iteration":923,"passed_time":2.240244511,"remaining_time":0.1842625356},
{"learn":[0.005915070325],"iteration":924,"passed_time":2.242164072,"remaining_time":0.1817970869},
{"learn":[0.005907773972],"iteration":925,"passed_time":2.244484514,"remaining_time":0.1793648532},
{"learn":[0.00589613989],"iteration":926,"passed_time":2.246623473,"remaining_time":0.1769185691},
{"learn":[0.005882626772],"iteration":927,"passed_time":2.248617812,"remaining_time":0.1744617268},
{"learn":[0.005873122066],"iteration":928,"passed_time":2.250815532,"remaining_time":0.1720214238},
{"learn":[0.005864586309],"iteration":929,"passed_time":2.25311516,"remaining_time":0.1695893131},
{"learn":[0.005851449072],"iteration":930,"passed_time":2.255139276,"remaining_time":0.1671370677},
{"learn":[0.005838435888],"iteration":931,"passed_time":2.257224306,"remaining_time":0.1646901854},
{"learn":[0.005828694254],"iteration":932,"passed_time":2.25954699,"remaining_time":0.1622611451},
{"learn":[0.005812419206],"iteration":933,"passed_time":2.26142126,"remaining_time":0.1598006458},
{"learn":[0.005804514885],"iteration":934,"passed_time":2.2636003,"remaining_time":0.1573625877},
{"learn":[0.005797173828],"iteration":935,"passed_time":2.265705612,"remaining_time":0.1549200418},
{"learn":[0.005789038539],"iteration":936,"passed_time":2.267820614,"remaining_time":0.1524788673},
{"learn":[0.005779245496],"iteration":937,"passed_time":2.26994924,"remaining_time":0.1500392888},
{"learn":[0.005770097673],"iteration":938,"passed_time":2.272059188,"remaining_time":0.1475991592},
{"learn":[0.005759078264],"iteration":939,"passed_time":2.274189166,"remaining_time":0.1451610106},
{"learn":[0.005751569197],"iteration":940,"passed_time":2.276513756,"remaining_time":0.1427357191},
{"learn":[0.005743379891],"iteration":941,"passed_time":2.278507837,"remaining_time":0.1402902914},
{"learn":[0.005734125525],"iteration":942,"passed_time":2.280533258,"remaining_time":0.1378477155},
{"learn":[0.005724966154],"iteration":943,"passed_time":2.282644206,"remaining_time":0.135411097},
{"learn":[0.005715685338],"iteration":944,"passed_time":2.284787479,"remaining_time":0.1329770491},
{"learn":[0.005704346299],"iteration":945,"passed_time":2.286956044,"remaining_time":0.1305450596},
{"learn":[0.005697195232],"iteration":946,"passed_time":2.289109441,"remaining_time":0.1281127776},
{"learn":[0.005686240643],"iteration":947,"passed_time":2.29119153,"remaining_time":0.1256771725},
{"learn":[0.005677604303],"iteration":948,"passed_time":2.29337482,"remaining_time":0.1232477511},
{"learn":[0.00566499047],"iteration":949,"passed_time":2.295583798,"remaining_time":0.1208201999},
{"learn":[0.005656567961],"iteration":950,"passed_time":2.297642464,"remaining_time":0.1183853636},
{"learn":[0.005646751449],"iteration":951,"passed_time":2.300044685,"remaining_time":0.1159686396},
{"learn":[0.005637860298],"iteration":952,"passed_time":2.30213485,"remaining_time":0.1135365561},
{"learn":[0.005628095567],"iteration":953,"passed_time":2.304363201,"remaining_time":0.1111118524},
{"learn":[0.005619360134],"iteration":954,"passed_time":2.306345027,"remaining_time":0.1086759437},
{"learn":[0.005611210316],"iteration":955,"passed_time":2.308465823,"remaining_time":0.106247381},
{"learn":[0.005603811145],"iteration":956,"passed_time":2.31058648,"remaining_time":0.1038194552},
{"learn":[0.005593385547],"iteration":957,"passed_time":2.312804619,"remaining_time":0.1013964447},
{"learn":[0.005582728237],"iteration":958,"passed_time":2.314930059,"remaining_time":0.09896989823},
{"learn":[0.005574794859],"iteration":959,"passed_time":2.317200241,"remaining_time":0.09655001005},
{"learn":[0.005566994101],"iteration":960,"passed_time":2.31913658,"remaining_time":0.09411688516},
{"learn":[0.005558913201],"iteration":961,"passed_time":2.321293511,"remaining_time":0.09169350667},
{"learn":[0.005550530553],"iteration":962,"passed_time":2.323359584,"remaining_time":0.08926719067},
{"learn":[0.005541174859],"iteration":963,"passed_time":2.325437677,"remaining_time":0.08684207092},
{"learn":[0.00553329438],"iteration":964,"passed_time":2.327659393,"remaining_time":0.08442287953},
{"learn":[0.005523066968],"iteration":965,"passed_time":2.329991575,"remaining_time":0.08200798504},
{"learn":[0.005514433235],"iteration":966,"passed_time":2.332093196,"remaining_time":0.07958539344},
{"learn":[0.005507139117],"iteration":967,"passed_time":2.334302125,"remaining_time":0.07716701241},
{"learn":[0.005500763282],"iteration":968,"passed_time":2.336271299,"remaining_time":0.07474139348},
{"learn":[0.005489600077],"iteration":969,"passed_time":2.338494661,"remaining_time":0.07232457715},
{"learn":[0.005481391773],"iteration":970,"passed_time":2.340554721,"remaining_time":0.06990328209},
{"learn":[0.005472901091],"iteration":971,"passed_time":2.342633219,"remaining_time":0.06748326146},
{"learn":[0.00546178855],"iteration":972,"passed_time":2.344685527,"remaining_time":0.06506321607},
{"learn":[0.005454476178],"iteration":973,"passed_time":2.34684028,"remaining_time":0.06264666046},
{"learn":[0.005448043719],"iteration":974,"passed_time":2.349010327,"remaining_time":0.06023103403},
{"learn":[0.005438690633],"iteration":975,"passed_time":2.3512392,"remaining_time":0.05781735738},
{"learn":[0.005429252982],"iteration":976,"passed_time":2.353608051,"remaining_time":0.05540735433},
{"learn":[0.005421037227],"iteration":977,"passed_time":2.355543481,"remaining_time":0.05298768567},
{"learn":[0.005415012687],"iteration":978,"passed_time":2.357800802,"remaining_time":0.05057591097},
{"learn":[0.005405078083],"iteration":979,"passed_time":2.359668539,"remaining_time":0.0481565008},
{"learn":[0.005398080871],"iteration":980,"passed_time":2.361916538,"remaining_time":0.04574558025},
{"learn":[0.005391176045],"iteration":981,"passed_time":2.364065574,"remaining_time":0.04333317754},
{"learn":[0.005382977426],"iteration":982,"passed_time":2.366165028,"remaining_time":0.04092045318},
{"learn":[0.005374306068],"iteration":983,"passed_time":2.368391914,"remaining_time":0.03851043762},
{"learn":[0.005365988612],"iteration":984,"passed_time":2.370774915,"remaining_time":0.03610317129},
{"learn":[0.005354645103],"iteration":985,"passed_time":2.372769748,"remaining_time":0.03369044268},
{"learn":[0.005345862359],"iteration":986,"passed_time":2.374726465,"remaining_time":0.03127805881},
{"learn":[0.005337961018],"iteration":987,"passed_time":2.376919913,"remaining_time":0.02886947262},
{"learn":[0.005326832086],"iteration":988,"passed_time":2.379112729,"remaining_time":0.02646131448},
{"learn":[0.005317915604],"iteration":989,"passed_time":2.381185367,"remaining_time":0.02405237745},
{"learn":[0.005310947821],"iteration":990,"passed_time":2.383335842,"remaining_time":0.02164482601},
{"learn":[0.005301488563],"iteration":991,"passed_time":2.38538941,"remaining_time":0.01923701137},
{"learn":[0.005289323628],"iteration":992,"passed_time":2.387792823,"remaining_time":0.0168323764},
{"learn":[0.005281281471],"iteration":993,"passed_time":2.389785937,"remaining_time":0.01442526723},
{"learn":[0.005273029208],"iteration":994,"passed_time":2.391788975,"remaining_time":0.01201904007},
{"learn":[0.005264338478],"iteration":995,"passed_time":2.393783869,"remaining_time":0.009613589837},
{"learn":[0.005255937576],"iteration":996,"passed_time":2.395677709,"remaining_time":0.007208659103},
{"learn":[0.005246036872],"iteration":997,"passed_time":2.397326265,"remaining_time":0.004804261052},
{"learn":[0.005238878727],"iteration":998,"passed_time":2.399077466,"remaining_time":0.002401478945},
{"learn":[0.005231449753],"iteration":999,"passed_time":2.400826049,"remaining_time":0}
]}